Workbook

Sheet 因子定义_旧
A1: 主题 | B1: 子主题 | C1: 信号代码 | D1: 信号说明 | E1: 代码 | F1: 生产使用 | G1: 操作 | H1: IC | I1: 优化后IC | J1: 优化/新增说明 | K1: 人员 | L1: 其他说明
A2: 成长 | C2: ar_over | D2: 异常隔夜回报 | E2: ar_over
A3: 成长 | C3: ar_over1 | D3: 异常隔夜回报（加入快报预告） | E3: ar_over1 | F3: 是
A4: 成长 | C4: cfg_ttm | D4: 经营性现金流净额ttm同比 | E4: cfg_ttm
A5: 成长 | C5: con_np_yoy_roll | D5: 滚动一致预期净利润同比增长率 | E5: con_forcast
A6: 成长 | C6: con_npcgrate_2y_roll | D6: 滚动一致预期净利润两年符合增长率 | E6: con_forcast
A7: 成长 | C7: con_or_yoy_roll | D7: 滚动营业收入同比增长率 | E7: con_forcast
A8: 成长 | C8: con_peg_roll | D8: 个股滚动净利润复合增长率/个股未来滚动PE | E8: con_forcast
A9: 成长 | C9: da2a | D9: (最新报告期总资产-上季度总资产)/上季度总资产 | E9: da2a
A10: 成长 | C10: da2ev | D10: （最新报告期总资产-去年总资产）/EV | E10: da2ev
A11: 成长 | C11: dafc2ia | D11: Delta(X)/Y：Delta(预收款项)/无形资产。adv_from_custXXXintang_assets | E11: finpattern | G11: 新增/删除/优化/不变
A12: 成长 | C12: de2e | D12: （净利润TTM-去年同期净利润TTM)/abs(去年同期净利润TTM))，净利润字段为净利润不含少数股东损益（TTM） | E12: de2e
A13: 成长 | C13: de2p | D13: （季度净利润-上年同期季度净利润）/最新总市值，净利润为净利润不含少数股东损益数据（季度) | E13: de2p | F13: 是
A14: 成长 | C14: dqop2qcpbe | D14: Delta(X)/Y：Delta(季度化(营业利润))/季度化(支付给职工以及为职工支付的现金)。oper_profit_qXXXcash_pay_beh_empl_q | E14: finpattern
A15: 成长 | C15: ds2ev | D15: （最新报告期季度营业收入-上年同期季度营业收入）/EV | E15: ds2ev | F15: 是
A16: 成长 | C16: ds2p | D16: （营业收入-去年同期营业收入）/最新总市值 | E16: ds2p
A17: 成长 | C17: ds2s | D17: （最新报告期季度营业收入-上年同期季度营业收入）/ABS（上年同期季度营业收入） | E17: ds2s
A18: 成长 | C18: egibs | D18: (明年一致预期净利润均值-当年一致预期净利润均值)/abs(当年一致预期净利润均值) | E18: egibs
A19: 成长 | C19: egro3 | D19: 过去3年净利润回归计算得到的增长率 | E19: egro3
A20: 成长 | C20: egro5 | D20: 年报每股净利润对时间的回归系数除以平均净利润绝对值,对因变量进行3倍中位数调整 | E20: egro5 | F20: 是
A21: 成长 | C21: epsg_ttm | D21: eps_ttm同比。NetProfit_ttm/TotalShr-L1Y_NetProfit_ttm/L1Y_TotalShr。删除掉一年间股本扩大5倍以上的 | E21: epsg_ttm | L21: 未生成信号
A22: 成长 | C22: fes1 | D22: fes1=(季度(净利润)/总股本-去年同期(季度(净利润))/去年同期总股本)/(去年同期总资产/去年同期总股本) | E22: fes1
A23: 成长 | C23: fes2 | D23: fes2=(季度(支付的各项税费)/总股本-去年同期(季度(支付的各项税费))/去年同期总股本)/(去年同期总资产/去年同期总股本) | E23: fes2
A24: 成长 | C24: ffretn | D24: 在财报公布日前2日到后一日，股票相对市场(二级行业)的特定回报,若是非交易日转到后1个交易日，都是4个交易日， | E24: ffretn
A25: 成长 | C25: ffretnind1 | D25: 同ffretn,相对一级行业 | E25: ffretnind1
A26: 成长 | C26: fg1 | D26: fg1=((预测EPS-净利润)/abs(净利润)+1)^(1/1)-1，只用年报数据 | E26: fg1
A27: 成长 | C27: fg2 | D27: fg2=((预测EPS-净利润)/abs(净利润)+1)^(1/2)-1，只用年报数据 | E27: fg2 | F27: 是
A28: 成长 | C28: fg3 | D28: fg3=((预测EPS-净利润)/abs(净利润)+1)^(1/3)-1，只用年报数据 | E28: fg3
A29: 成长 | C29: kfes1 | D29: （每股季度扣非净利润-去年同期每股季度扣非净利润）/每股总资产 | E29: kfes1
A30: 成长 | C30: kqdroa | D30: Ydelta（（季度营业总收入-季度营业总成本+财务费用）/最近两季度总资产平均值） | E30: kqdroa | L30: 逻辑可能有问题？和qdroa的区别？
A31: 成长 | C31: kqdroe | D31: Ydelta（季度扣除非经常性损益后净利润NET_PROFIT_AFTER_DED_NR_LP/最近两季度股东权益合计(不含少数股东权益)） | E31: kqdroe
A32: 反转 | C32: mom1_con_pb_roll | D32: 最新分析师一致预期滚动BP/1月前分析师一致预期滚动BP-1。和reversal_price相关性达0.7，归入反转中 | E32: mom_con_forcast | F32: 不变
A33: 反转 | C33: mom1_con_pe_roll | D33: 最新分析师一致预期滚动EP/1月前分析师一致预期滚动EP-1。和reversal_price相关性达0.7，归入反转中 | E33: mom_con_forcast | F33: 不变
A34: 反转 | C34: mom1_con_ps_roll | D34: 最新分析师一致预期滚动SP/1月前分析师一致预期滚动SP-1。和reversal_price相关性达0.7，归入反转中 | E34: mom_con_forcast | F34: 不变
A35: 反转 | C35: mom3_con_pb_roll | D35: 最新分析师一致预期滚动BP/3月前分析师一致预期滚动BP-1。和reversal_price相关性达0.7，归入反转中 | E35: mom_con_forcast | F35: 不变
A36: 反转 | C36: mom3_con_pe_roll | D36: 最新分析师一致预期滚动EP/3月前分析师一致预期滚动EP-1。和reversal_price相关性达0.7，归入反转中 | E36: mom_con_forcast | F36: 不变
A37: 反转 | C37: mom3_con_ps_roll | D37: 最新分析师一致预期滚动SP/3月前分析师一致预期滚动SP-1。和reversal_price相关性达0.7，归入反转中 | E37: mom_con_forcast | F37: 不变
A38: 成长 | C38: nde2p | D38: （净利润-上年同期净利润）/总市值，净利润为归属于母公司的净利润的季度化数据，使用了快报和预告数据。 | E38: nde2p
A39: 成长 | C39: nds2ev | D39: 营业收入同比变化/EV，使用了快报和预告数据 | E39: nds2ev
A40: 成长 | C40: ne2e_q | D40: 单季度净利润增长率，使用了预告快报信息 | E40: ne2e_q
A41: 成长 | C41: nfes1 | D41: 净利润同比变化/总资产，总资产使用年报数据。净利润如果有快报或者预告数据，则优先使用该数据。 | E41: nfes1
A42: 成长 | C42: npegl | D42: 同pegl | E42: npeg
A43: 成长 | C43: npegs | D43: 同pegs | E43: npeg
A44: 成长 | C44: npg_q | D44: 季度净利润同比增长，分母最小为1000万。 | E44: npg_q | L44: 未生成
A45: 成长 | C45: npg_ttm | D45: 净利润ttm同比增长，分母最小为1000万。 | E45: npg_ttm
A46: 成长 | C46: nqcsg | D46: q，因为预告公布的是营业总收入，这里使用营业总收入。使用了快报和预告数据 | E46: nqcsg | F46: 是
A47: 成长 | C47: nqdroe | D47: 注意有可能股东权益还没公布（如预告），此时na.rm=T。使用了快报和预告数据 | E47: nqdroe | F47: 是
A48: 成长 | C48: opg_q | D48: （季度营业利润-上年同期季度营业利润）/abs(上年统计季度营业利润） | E48: opg_q | L48: 重新生成，未中性化
A49: 成长 | C49: opg_ttm | D49: 营业利润ttm同比 | E49: opg_ttm
A50: 成长 | C50: org_ttm | D50: 营业收入ttm同比 | E50: org_ttm
A51: 成长 | C51: pegl | D51: 未来2年一致预期净利润年化增长率除以市盈率，对于由负转正的缺失，相当于用均值补全效果，预测和实际利润均为负或者增长率、市盈率同时为负的设为-10 | E51: pegl | F51: 是
A52: 成长 | C52: pegs | D52: 未来一年一致预期净利润年化增长率除以市盈率 | E52: pegs | F52: 是
A53: 成长 | C53: q_or_stb | D53: 8期季度营业收入同比增速均值/标准差 | E53: q_or_stb | L53: 重新生成，未中性化
A54: 成长 | C54: qcsg | D54: qcsg=((季度(营业收入)-去年同期(季度(营业收入)))/abs(去年同期(季度(营业收入)))，相当于org_q | E54: qcsg
A55: 成长 | C55: qdroa | D55: roa=(季度(营业利润)+季度(财务费用))/两季度平均(总资产) qdroa=YearDelta(roa) | E55: qdroa
A56: 成长 | C56: qdroe | D56: roe=季度(归母净利润)/两季度平均(归母所有者权益) qdroe=YearDelta(roe) | E56: qdroe
A57: 成长 | C57: qe_stb | D57: 8期季度净利润同比增速均值/标准差 | E57: qe_stb | L57: 重新生成，未中性化
A58: 成长 | C58: qop_acc | D58: 8期季度营业利润对时间回归的二次项系数，lm(qe~t^2+t) | E58: qop_acc | L58: 重新生成，未中性化
A59: 成长 | C59: qop_dsd | D59: 一阶差分（8期季度营业利润同比增速均值/标准差） | E59: qop_dsd | L59: 重新生成，未中性化
A60: 成长 | C60: qop_stb | D60: 8期季度营业利润同比增速均值/标准差 | E60: qop_stb | L60: 重新生成，未中性化
A61: 成长 | C61: qop2qlgae | D61: X/Y：季度化(营业利润)/季度化(管理费用)。oper_profit_qXXXless_gerl_admin_exp_q | E61: finpattern
A62: 成长 | C62: qor_acc | D62: 8期季度营业收入对时间回归的二次项系数，lm(qe~t^2+t) | E62: qor_acc | L62: 重新生成，未中性化
A63: 成长 | C63: qor_dsd | D63: 一阶差分（8期季度营业收入同比增速均值/标准差） | E63: qor_dsd | L63: 重新生成，未中性化
A64: 成长 | C64: qtor2qtoc | D64: X/Y：季度化(营业总收入)/季度化(营业总成本)。tot_oper_rev_qXXXtot_oper_cost_q | E64: finpattern
A65: 成长 | C65: reg_con_np | D65: 来源天风，通过回归法计算企业的两年复合增长率。以最小二乘法拟合点列(1,Profit_FY0)，(2,Profit_FY1)，(3,Profit_FY2)的线性方程;同时我们添加约束条件使得回归方程通过点(1,Profit_FY0)。系数b的拟合值푏即为企业每年的净利润增长额度，将푏除以三年净利润Profit_FY0，Profit_FY1，Profit_FY2平均值即得到企业的预期复合增长率,系数可化简为b=0.4∗(fy2-fy1)+0.6∗(fy1−fy0)因此，回归系数b实质上就是企业在前后两个年度净利润增长值的加权平均，将系数除以三年的平均净利润即得到增长率Growth=b/(y0+y1+y2)/3 | E65: reg_con_np | F65: 是
A66: 成长 | C66: reg_con_np1 | D66: 同reg_con_np，分母最小5000万 | E66: reg_con_np1
A67: 成长 | C67: reg_con_or | D67: 回归计算一致预期营业收入复合增长率 | E67: reg_con_or | F67: 是
A68: 成长 | C68: reg_con_or1 | D68: 回归计算一致预期营业收入复合增长率，调整平均收入最低为10000万 | E68: reg_con_or1
A69: 成长 | C69: rgrowth | D69: barra | E69: cne5_factors
A70: 成长 | C70: roeg_ttm | D70: roe=TTM(归母净利润)/两年平均(归母所有者权益) roeg_ttm=YearDelta(roe) | E70: roeg_ttm | L70: 重新生成，未中性化
A71: 反转 | C71: rpegl | D71: rpegl=Z_SCORE(pegl, 最近一年) | E71: rpegl
A72: 反转 | C72: rpegs | D72: rpegs=Z_SCORE(pegs, 最近一年) | E72: rpegs | F72: 是
A73: 成长 | C73: rqnp_rqcpbe | D73: Delta(X)-Delta(Y)：Delta(季度化(净利润(不含少数股东损益)))-Delta(季度化(支付给职工以及为职工支付的现金))。net_profit_excl_min_int_inc_q_rXXXcash_pay_beh_empl_q_r | E73: finpattern
A74: 成长 | C74: rqop_rcpg | D74: Delta(X)-Delta(Y)：Delta(季度化(营业利润))-Delta(季度化(购买商品、接受劳务支付的现金))。oper_profit_q_rXXXcash_pay_goods_purch_serv_rec_q_r | E74: finpattern
A75: 成长 | C75: rqop_rqcpbe | D75: Delta(X)-Delta(Y)：Delta(季度化(营业利润))-Delta(季度化(支付给职工以及为职工支付的现金))。oper_profit_q_rXXXcash_pay_beh_empl_q_r | E75: finpattern
A76: 成长 | C76: rqop_rqlgae | D76: Delta(X)-Delta(Y)：Delta(季度化(营业利润))-Delta(季度化(管理费用))。oper_profit_q_rXXXless_gerl_admin_exp_q_r | E76: finpattern
A77: 成长 | C77: rrqop_qcpacf | D77: residue of linear regression(季度化(营业利润)~季度化(购建固定资产、无形资产和其他长期资产支付的现金)+1)。oper_profit_qXXXcash_pay_acq_const_fiolta_q | E77: finpattern
A78: 成长 | C78: rrqop_qncfoa | D78: residue of linear regression(季度化(营业利润)~季度化(经营活动产生的现金流量净额)+1)。oper_profit_qXXXnet_cash_flows_oper_act_q | E78: finpattern
A79: 成长 | C79: sgro3 | D79: 3年回归 | E79: sgro3
A80: 成长 | C80: sgro5 | D80: 过去5年年报每股营业收入对时间的回归系数 | E80: sgro5 | F80: 是
A81: 成长 | C81: smarg | D81: arg=季度(营业收入)-季度变化(应收账款) smarg=Z_SCORE(年度同比变化率(arg), 最近16个季度)。 sg=sales-应收账款（单季度数据，bs），求sg单季同比，再求同比的z_score.(数据长度：16个季度）,历史相对现金收入变化，oper_rev-当季acct_rcv | E81: smarg | F81: 是
A82: 成长 | C82: sue | D82: sue=Z_SCORE(年度同比变化(季度(净利润)), 最近8个季度）。历史季度盈利惊喜,z_score(净利润-上年同期净利润）（用过去8个季度数据估算）,金融企业没有数据？ | E82: sue
A83: 成长 | C83: suoi | D83: suoi=Z_SCORE(季度(总营业收入-总营业成本), 最近8个季度） | E83: suoi | F83: 是
A84: 成长 | C84: sup_con_np | D84: 定期报告（不含预告和快报）相对分析师预测数据的增长 | E84: sup_con_np | F84: 是
A85: 成长 | C85: sup_con_np_yg | D85: 定期报告（含预告和快报）相对分析师预测数据的增长 | E85: sup_con_np_yg
A86: 成长 | C86: supad | D86: 预收账款adv_from_cust/平均总资产，再求z_score | E86: supad | F86: 是
A87: 成长 | C87: sus | D87: sue=Z_SCORE(年度同比变化(季度(营业收入)), 最近8个季度） | E87: sus | F87: 是
A88: 分析师 | B88: rec | C88: brkgs | D88: 券商金股,根据调入调出家数进行赋值，加总得到总分 | E88: brkgs
A89: 分析师 | B89: cov | C89: cvg | D89: n个月覆盖度（同一机构不同日期算多次） | E89: cvg | G89: 删除 | I89: 0.018 | J89: 可以使用cvg_og，只考虑机构数，表现也更好一些
A90: 分析师 | B90: cov | C90: cvg_og3 | D90: 3个月覆盖度,机构数 | E90: cvg_og | F90: 是 | G90: 不变 | I90: 0.02 | J90: 对1-4个月进行遍历，从覆盖度和表现上目前3个月合理
A91: 分析师 | B91: drec | C91: darec | D91: 评级变动加权（darec_l:所有机构，180工作日，60半衰期;darec: 所有机构,180工作日，30半衰期;darec_w: 所有机构，90工作日，30半衰期;darec_s） | E91: darec | F91: 是 | G91: 删除 | I91: \ | J91: 代码合并，与darec_l相关性很高，不保存
A92: 分析师 | B92: drec | C92: darec_l | D92: 评级变动加权（darec_l:所有机构，180工作日，60半衰期;darec: 所有机构,180工作日，30半衰期;darec_w: 所有机构，90工作日，30半衰期;darec_s） | E92: darec | F92: 是 | G92: 优化 | H92: 0.0087 | I92: 0.0093 | J92: 代码合并，使用100工作日，半衰期60工作日，改名darec100_60
A93: 分析师 | B93: drec | C93: darec_s | D93: 评级变动加权（darec_l:所有机构，180工作日，60半衰期;darec: 所有机构,180工作日，30半衰期;darec_w: 所有机构，90工作日，30半衰期;darec_s） | E93: darec | F93: 是 | G93: 优化 | H93: 0.0091 | I93: 0.0099 | J93: 代码合并，使用20工作日，半衰期10工作日，改名为darec20_10，与darec80_30比较
A94: 分析师 | B94: drev | C94: darev | D94: 盈利预测同比变化/总市值(darev:90天，30半衰期;darev_l: 120天，60半衰期;darev_s: 40天，10半衰期;添加darev_num_hl:num工作日内的预测，hl半衰期加权) | E94: darev | F94: 是 | G94: 优化 | H94: \ | I94: 0.0225 | J94: 代码合并，与darev_l相关性很高,去掉，添加darev_60_20,不做比较
A95: 分析师 | B95: drev | C95: darev_l | D95: 盈利预测同比变化/总市值(darev:90天，30半衰期;darev_l: 120天，60半衰期;darev_s: 40天，10半衰期;添加darev_num_hl:num工作日内的预测，hl半衰期加权) | E95: darev | F95: 是 | G95: 优化 | H95: 0.0219 | I95: 0.022 | J95: 代码合并，参数改为120工作日，半衰期60工作日，命名为darev_120_60,与80_40工作日比较
A96: 分析师 | B96: drev | C96: darev_s | D96: 盈利预测同比变化/总市值(darev:90天，30半衰期;darev_l: 120天，60半衰期;darev_s: 40天，10半衰期;添加darev_num_hl:num工作日内的预测，hl半衰期加权) | E96: darev | F96: 是 | G96: 优化 | H96: 0.0208 | I96: 0.0208 | J96: 代码合并，参数改为40工作日，半衰期10工作日，命名为darev_40_10,与20_10工作日比较
A97: 分析师 | B97: drec | C97: drec | D97: 最新一致预期评级变化,这个月评级-上个月 | E97: drec | G97: 不变 | I97: 0.0061
A98: 分析师 | B98: dispersion | C98: eps_variability2 | D98: n个月分析师分歧度,至少3家覆盖 | E98: eps_variability | F98: 是 | G98: 不变 | I98: 0.0109 | J98: 测试1/2/3/6/9个月
A99: 分析师 | B99: drev | C99: grev3 | D99: 盈利预测变动(相比1个月前grev,3个月前grev3) | E99: grev | G99: 不变 | I99: 0.018 | J99: 测试了1-6个月，1、6明显差一些，其他差别不大
A100: 分析师 | B100: rec | C100: intretp | D100: 内部分析师,1个月内调入或调出的、持有的分别打分 | E100: intretp
...

Sheet 因子梳理
A1: 主题 | B1: 子主题 | C1: 信号代码 | D1: 信号说明 | E1: 代码 | F1: 生产使用 | G1: 操作 | H1: IC.Broad | I1: IC.ZZ800 | J1: 优化后IC | K1: 优化/新增说明 | L1: 人员 | M1: 其他说明 | N1: 相关字段 | O1: 字段类别 | P1: 计算方法
A2: 成长 | C2: nde2p | D2: 季度净利润同比变化占总市值比，定义同de2p，增加快报和预告数据。nde2p =（净利润-上年同期净利润）/总市值，净利润为归属于母公司的净利润的季度化数据，使用了快报和预告数据。 | E2: nde2p | I2: 0.05 | N2: net_profit_excl_min_int_inc | O2: Q | P2: 同比变化占比
A3: 成长 | C3: ne2e_q | D3: 季度净利润同比增长率，使用了预告快报信息 | E3: ne2e_q | I3: 0.049 | N3: net_profit_excl_min_int_inc | O3: Q | P3: 同比增长率
A4: 成长 | C4: npegl | D4: 同pegl | E4: npeg | I4: 0.047 | P4: 比值
A5: 成长 | C5: sup_con_np_yg | D5: 定期报告（含预告和快报）相对分析师预测数据的增长 | E5: sup_con_np_yg | I5: 0.047 | N5: con_np,net_profit_excl_min_int_inc | O5: RAW | P5: 超预期
A6: 成长 | C6: de2p | D6: 季度净利润同比变化/最新总市值， (Q(净利润) - L1Y_Q(净利润))/总市值 | E6: de2p | F6: 是 | I6: 0.044 | N6: net_profit_excl_min_int_inc | O6: Q | P6: 同比变化占比
A7: 成长 | C7: nqdroe | D7: 注意有可能股东权益还没公布（如预告），此时na.rm=T。使用了快报和预告数据季度ROE同比变化。qroe=季度(归母净利润)/两季度平均(归母所有者权益) qdroe=YearDelta(roe)=qroe-L1Y_qroe | E7: nqdroe | F7: 是 | I7: 0.043 | P7: 同比变化
A8: 成长 | C8: nfes1 | D8: 净利润同比变化/总资产，总资产使用年报数据。净利润如果有快报或者预告数据，则优先使用该数据。和kfes1和fes1使用季度净利润不同，此处使用的是净利润同比变化。 | E8: nfes1 | I8: 0.041 | N8: net_profit_excl_min_int_inc | O8: RAW | P8: 同比变化占比
A9: 成长 | C9: opg_q | D9: 季度营业利润同比增长率。Opq_q = (Q(营业利润)-L1Y_Q(营业利润))/abs(L1Y_Q(营业利润)） | E9: opg_q | I9: 0.041 | N9: oper_profit | O9: Q | P9: 同比增长率
A10: 成长 | C10: qdroe | D10: 季度ROE同比变化。qroe=季度(归母净利润)/两季度平均(归母所有者权益) qdroe=YearDelta(roe)=qroe-L1Y_qroe | E10: qdroe | I10: 0.04 | N10: net_profit_excl_min_int_inc,tot_assets | O10: Q | P10: 同比变化
A11: 成长 | C11: sue | D11: sue=Z_SCORE(年度同比变化(季度(净利润)), 最近8个季度）。历史季度盈利惊喜,z_score(净利润-上年同期净利润）（用过去8个季度数据估算） | E11: sue | I11: 0.04 | N11: net_profit_excl_min_int_inc | O11: Q | P11: 超预期
A12: 成长 | C12: da2a | D12: 总资产季度环比增长率,(F-L1Q_F)/L1Q_F | E12: da2a | I12: 0.039 | N12: tot_shrhldr_eqy_excl_min_int | O12: RAW | P12: 环比增长率
A13: 成长 | C13: suoi | D13: suoi=Z_SCORE(季度(总营业收入-总营业成本), 最近8个季度） | E13: suoi | F13: 是 | I13: 0.039 | N13: tot_oper_rev,tot_oper_cost | O13: Q | P13: 超预期
A14: 成长 | C14: qop2qlgae | D14: X/Y：季度化(营业利润)/季度化(管理费用)。oper_profit_qXXXless_gerl_admin_exp_q | E14: finpattern | I14: 0.038 | N14: oper_profit_q,less_gerl_admin_exp_q | O14: Q | P14: 比值
A15: 成长 | C15: fes1 | D15: 每股季度净利润同比变化占每股总资产比例，fes1=(季度(净利润)/总股本-去年同期(季度(净利润))/去年同期总股本)/(去年同期总资产/去年同期总股本) | E15: fes1 | I15: 0.037 | N15: net_profit_incl_min_int_inc,total_assets | O15: Q | P15: 同比变化占比
A16: 成长 | C16: kfes1 | D16: 每股季度扣非净利润同比变化占每股总资产比例 ,（每股季度扣非净利润-去年同期每股季度扣非净利润）/每股总资产 | E16: kfes1 | I16: 0.037 | N16: net_profit_after_ded_nr_lp,total_assets | O16: Q | P16: 同比变化占比
A17: 成长 | C17: kqdroa | D17: kqroa的同比变化。kqroa = （季度营业总收入-季度营业总成本+财务费用）/最近两季度总资产平均值。Kqdroa = kqroa-L1Y_kqroa | E17: kqdroa | I17: 0.037 | N17: tot_oper_rev,tot_oper_cost,less_fin_exp,total_assets | O17: Q | P17: 同比变化
A18: 成长 | C18: kqdroe | D18: kqroe的同比变化。Kqroe=（季度扣除非经常性损益后净利润/最近两季度股东权益合计(不含少数股东权益)）。Kqdroe = kqroe-L1Y_kqroe | E18: kqdroe | I18: 0.037 | N18: net_profit_after_ded_nr_lp,tot_shrhldr_eqy_excl_min_int | O18: Q | P18: 同比变化
A19: 成长 | C19: npegs | D19: 同pegs | E19: npeg | I19: 0.037 | P19: 比值
A20: 成长 | C20: dqop2qcpbe | D20: Delta(X)/Y：Delta(季度化(营业利润))/季度化(支付给职工以及为职工支付的现金)。oper_profit_qXXXcash_pay_beh_empl_q | E20: finpattern | I20: 0.036 | N20: oper_profit,cash_pay_beh_empl_q | O20: Q | P20: 同比变化占比
A21: 成长 | C21: qdroa | D21: 季度ROA同比变化。qroa=(季度(营业利润)+季度(财务费用))/两季度平均(总资产) qdroa=YearDelta(qroa)=qroa-L1Y-qroa | E21: qdroa | I21: 0.036 | N21: oper_profit,less_fin_exp,tot_assets | O21: Q | P21: 同比变化
A22: 成长 | C22: rrqop_qcpacf | D22: 特质利润。residue of linear regression(季度化(营业利润)~季度化(购建固定资产、无形资产和其他长期资产支付的现金)+1)。oper_profit_qXXXcash_pay_acq_const_fiolta_q | E22: finpattern | I22: 0.036 | N22: oper_profit,cash_pay_acq_const_fiolta | O22: Q | P22: 增长率对比
A23: 成长 | C23: rrqop_qncfoa | D23: 特质利润。residue of linear regression(季度化(营业利润)~季度化(经营活动产生的现金流量净额)+1)。oper_profit_qXXXnet_cash_flows_oper_act_q | E23: finpattern | I23: 0.036 | N23: oper_profit,net_cash_flows_oper_act | O23: Q | P23: 统计指标
A24: 成长 | C24: nds2ev | D24: 营业收入同比变化/EV，使用了快报和预告数据 | E24: nds2ev | I24: 0.035 | N24: net_profit_excl_min_int_inc | O24: Q | P24: 同比变化占比
A25: 成长 | C25: qtor2qtoc | D25: X/Y：季度化(营业总收入)/季度化(营业总成本)。tot_oper_rev_qXXXtot_oper_cost_q | E25: finpattern | I25: 0.035 | N25: tot_oper_rev,tot_oper_cost | O25: Q | P25: 比值
A26: 成长 | C26: sup_con_np | D26: 定期报告（不含预告和快报）相对分析师预测数据的增长 | E26: sup_con_np | F26: 是 | I26: 0.035 | N26: con_np,net_profit_excl_min_int_inc | O26: RAW | P26: 超预期
A27: 成长 | C27: ds2ev | D27: 季度营业收入同比变化/EV, (Q(营业收入)-L1Y_Q(营业收入))/EV | E27: ds2ev | F27: 是 | I27: 0.034 | N27: oper_rev,ev | O27: Q | P27: 同比变化占比
A28: 成长 | C28: ar_over1 | D28: 异常隔夜回报（加入快报预告） | E28: ar_over1 | F28: 是 | G28: 不变 | I28: 0.033 | P28: 财报事件
A29: 成长 | C29: pegl | D29: 未来2年一致预期净利润年化增长率除以市盈率，对于由负转正的缺失，相当于用均值补全效果，预测和实际利润均为负或者增长率、市盈率同时为负的设为-10 | E29: pegl | F29: 是 | I29: 0.033 | P29: 比值
A30: 成长 | C30: nqcsg | D30: 季度营业总收入同比增长率。 | E30: nqcsg | F30: 是 | I30: 0.032 | P30: 同比增长率
A31: 成长 | C31: rqnp_rqcpbe | D31: 同比增长率(X)-同比增长率(Y)，RatioXMinusRatioY模式。季度净利润同比增长率-季度支付给职工以及为职工支付的现金同比增长率。此处衡量两个不同财务项的同比增长率差值。同比增长率=(F-L1Y_F)/abs(L1Y_F)。net_profit_excl_min_int_inc_q_rXXXcash_pay_beh_empl_q_r | E31: finpattern | I31: 0.032 | N31: net_profit_excl_min_int_inc,cash_pay_beh_empl | O31: Q | P31: 增长率对比
A32: 成长 | C32: rqop_rqcpbe | D32: 同比增长率(X)-同比增长率(Y)，RatioXMinusRatioY模式。季度营业利润同比增长率-季度支付给职工以及为职工支付的现金同比增长率。此处衡量两个不同财务项的同比增长率差值。同比增长率=(F-L1Y_F)/abs(L1Y_F)。oper_profit_q_rXXXcash_pay_beh_empl_q_r | E32: finpattern | I32: 0.032 | N32: oper_profit,cash_pay_beh_empl | O32: Q | P32: 增长率对比
A33: 成长 | C33: rqop_rqlgae | D33: 同比增长率(X)-同比增长率(Y)，RatioXMinusRatioY模式。季度营业利润同比增长率-季度管理费用同比增长率。此处衡量两个不同财务项的同比增长率差值。同比增长率=(F-L1Y_F)/abs(L1Y_F)。 oper_profit_q_rXXXless_gerl_admin_exp_q_r | E33: finpattern | I33: 0.031 | N33: oper_profit,less_gerl_admin_exp | O33: Q | P33: 增长率对比
A34: 成长 | C34: ar_over | D34: 异常隔夜回报 | E34: ar_over | G34: 不变 | I34: 0.029 | P34: 财报事件
A35: 成长 | C35: con_peg_roll | D35: 个股滚动净利润复合增长率/个股未来滚动PE | E35: con_forcast | I35: 0.029 | N35: con_peg_roll | P35: 比值
A36: 成长 | C36: rqop_rcpg | D36: 同比增长率(X)-同比增长率(Y)，RatioXMinusRatioY模式。季度营业利润同比增长率-季度购买商品、接收劳务支付的现金同比增长率。此处衡量两个不同财务项的同比增长率差值。同比增长率=(F-L1Y_F)/abs(L1Y_F)。oper_profit_q_rXXXcash_pay_goods_purch_serv_rec_q_r | E36: finpattern | I36: 0.029 | N36: oper_profit,cash_pay_goods_purch_serv_rec | O36: Q | P36: 增长率对比
A37: 成长 | C37: ds2p | D37: 营业收入同比变化/总市值, (营业收入-L1Y_营业收入)/总市值 | E37: ds2p | I37: 0.027 | N37: oper_rev | O37: RAW | P37: 同比变化占比
A38: 成长 | C38: npg_q | D38: 季度净利润同比增长率，分母最小为1000万。 | E38: npg_q | I38: 0.026 | N38: net_profit_excl_min_int_inc | O38: Q | P38: 同比增长率
A39: 成长 | C39: org_ttm | D39: TTM营业收入同比增长率，分母最小为1000万。 | E39: org_ttm | I39: 0.026 | N39: oper_rev | O39: TTM | P39: 同比增长率
A40: 成长 | C40: da2ev | D40: 总资产年度同比变化/EV, (F-L1Y_F)/EV | E40: da2ev | I40: 0.024 | N40: tot_assets | O40: RAW | P40: 同比变化占比
A41: 成长 | C41: opg_ttm | D41: TTM营业利润同比增长率。 | E41: opg_ttm | I41: 0.023 | N41: oper_profit | O41: TTM | P41: 同比增长率
A42: 成长 | C42: pegs | D42: 未来一年一致预期净利润年化增长率除以市盈率 | E42: pegs | F42: 是 | I42: 0.024 | P42: 比值
A43: 成长 | C43: dafc2ia | D43: Delta(X)/Y：Delta(预收款项)/无形资产。adv_from_custXXXintang_assets | E43: finpattern | G43: 新增 | I43: 0.022 | N43: adv_from_cust,intang_assets | P43: 同比变化占比
A44: 成长 | C44: qop_dsd | D44: 一阶差分（8期季度营业利润同比增长率均值/标准差） | E44: qop_dsd | I44: 0.023 | N44: oper_profit | O44: Q | P44: 统计指标
A45: 成长 | C45: roeg_ttm | D45: TTM(ROE)同比变化。roe=TTM(归母净利润)/两年平均(归母所有者权益) roeg_ttm=YearDelta(roe)。算法同qdroe | E45: roeg_ttm | I45: 0.02 | N45: net_profit_excl_min_int_inc,tot_shrhldr_eqy_excl_min_int | O45: TTM | P45: 同比变化
A46: 成长 | C46: qe_stb | D46: 8期季度净利润同比增长率均值/标准差 | E46: qe_stb | I46: 0.021 | N46: net_profit_excl_min_int_inc | O46: Q | P46: 统计指标
A47: 成长 | C47: qop_stb | D47: 8期季度营业利润同比增长率均值/标准差 | E47: qop_stb | I47: 0.021 | N47: oper_profit | O47: Q | P47: 统计指标
A48: 成长 | C48: qop_acc | D48: 8期季度营业利润对时间回归的二次项系数，lm(qe~t^2+t) | E48: qop_acc | I48: 0.015 | N48: oper_profit | O48: Q | P48: 统计指标
A49: 成长 | C49: cfg_ttm | D49: TTM经营性现金流净额同比增长率,(TTM(F) - (L1Y_TTM(F)))/abs(L1Y_TTM(F)) | E49: cfg_ttm | I49: 0.019 | N49: net_cash_flows_oper_act | O49: TTM | P49: 同比增长率
A50: 成长 | C50: de2e | D50: TTM净利润（不含少数股东权益）同比增长率，(TTM(F)-TTM(L1Y_F))/abs(TTM(L1Y_F)) | E50: de2e | I50: 0.019 | N50: net_profit_excl_min_int_inc | O50: TTM | P50: 同比增长率
A51: 成长 | C51: qcsg | D51: 季度营业收入同比增长率。qcsg=(Q(营业收入)-L1Y_Q(营业收入))/abs(L1Y_Q(营业收入))。应该比org_ttm好？ | E51: qcsg | I51: 0.019 | N51: oper_rev | O51: Q | P51: 同比增长率
A52: 成长 | C52: epsg_ttm | D52: TTM（EPS）同比变化。(TTM（净利润 ）/总股本-L1Y_TTM（净利润）/L1Y_总股本。删除掉一年间股本扩大5倍以上的。 | E52: epsg_ttm | I52: 0.018 | N52: net_profit_incl_min_int_inc | O52: TTM | P52: 同比变化
A53: 成长 | C53: npg_ttm | D53: TTM净利润同比增长率，分母最小为1000万。 | E53: npg_ttm | I53: 0.016 | N53: net_profit_excl_min_int_inc | O53: TTM | P53: 同比增长率
A54: 成长 | C54: npg3_ttm | D54: TTM净利润相比3年前的增长率，分母最小为1000万。 | E54: npg3_ttm | I54: 0.016 | N54: net_profit_excl_min_int_inc | O54: TTM | P54: 同比增长率
A55: 成长 | C55: con_np_yoy_roll | D55: 滚动一致预期净利润同比增长率 | E55: con_forcast | I55: 0.014 | N55: con_np_yoy_roll | O55: con_forecast_roll_stk | P55: 同比增长率
A56: 成长 | C56: smarg | D56: arg=季度(营业收入)-季度(应收账款)（应收账款季度变化） smarg=Z_SCORE(arg同比增长率, 最近16个季度)。 当前营业收入相对历史16期平均Z值。,金融企业没有数据？ | E56: smarg | F56: 是 | I56: 0.016 | N56: acct_rcv,oper_rev | O56: Q | P56: 超预期
A57: 成长 | C57: sus | D57: sus=Z_SCORE(年度同比变化（季度营业收入），最近8个季度）。 | E57: sus | F57: 是 | I57: 0.028 | N57: oper_rev | O57: Q | P57: 超预期
A58: 成长 | C58: fes2 | D58: 每股季度支付的各项税费同比变化占每股总资产比例，fes2=(季度(支付的各项税费)/总股本-去年同期(季度(支付的各项税费))/去年同期总股本)/(去年同期总资产/去年同期总股本) | E58: fes2 | I58: 0.014 | N58: pay_all_typ_tax,total_assets | O58: Q | P58: 同比变化占比
A59: 成长 | C59: ffretnind1 | D59: 同ffretn,相对一级行业 | E59: ffretnind1 | I59: 0.014 | O59: NA | P59: 财报事件
A60: 成长 | C60: ds2s | D60: 季度营业收入环比增长率,(Q(营业收入)-L1Y_Q(营业收入))/ABS(Q（营业收入）） | E60: ds2s | I60: 0.014 | N60: oper_rev | O60: Q | P60: 环比增长率
A61: 成长 | C61: con_or_yoy_roll | D61: 滚动营业收入同比增长率 | E61: con_forcast | I61: 0.013 | N61: con_or_yoy_roll | P61: 同比增长率
A62: 成长 | C62: rgrowth | D62: barra | E62: cne5_factors | I62: 0.011 | P62: 同比增长率
A63: 成长 | C63: supad | D63: 预收账款同比变化/平均总资产，再求z_score，16期 | E63: supad | F63: 是 | I63: 0.014 | N63: adv_from_cust,tot_assets | O63: RAW | P63: 超预期
A64: 成长 | C64: ffretn | D64: 在财报公布日前2日到后一日，股票相对市场(二级行业)的特定回报,若是非交易日转到后1个交易日，都是4个交易日， | E64: ffretn | I64: 0.013 | O64: NA | P64: 财报事件
A65: 成长 | C65: reg_con_or | D65: 回归计算一致预期营业收入复合增长率 | E65: reg_con_or | F65: 是 | I65: 0.009 | N65: con_or | O65: con_forecast_stk | P65: 同比增长率
A66: 成长 | C66: reg_con_or1 | D66: 回归计算一致预期营业收入复合增长率，调整平均收入最低为10000万 | E66: reg_con_or1 | I66: 0.009 | N66: con_or | O66: con_forecast_stk | P66: 同比增长率
A67: 成长 | C67: qor_stb | D67: 8期季度营业收入同比增长率均值/标准差 | E67: qor_stb | I67: 0.021 | N67: oper_rev | O67: Q | P67: 统计指标
A68: 成长 | C68: fg1 | D68: ((NetProtif_Forecast-NetProfit)/abs(NetProfit)+1)^(1/N)-1，N=1。只用年报数据 | E68: fg | I68: 0.009 | O68: RAW | P68: 同比增长率
A69: 成长 | C69: fg3 | D69: ((NetProtif_Forecast-NetProfit)/abs(NetProfit)+1)^(1/N)-1，N=3。只用年报数据 | E69: fg | I69: 0.008 | O69: RAW | P69: 同比增长率
A70: 成长 | C70: qor_dsd | D70: 一阶差分（8期季度营业收入同比增长率均值/标准差） | E70: qor_dsd | I70: 0.015 | N70: oper_rev | O70: Q | P70: 统计指标
A71: 成长 | C71: sgro5 | D71: 回归计算的最近5年复合增长率，只取年报数据。LM(总营业收入~T+1），取T的回归系数 | E71: sgro5 | F71: 是 | I71: 0.008 | N71: tot_oper_rev | O71: RAW | P71: 同比增长率
A72: 成长 | C72: reg_con_np1 | D72: 同reg_con_np，分母最小5000万 | E72: reg_con_np1 | I72: 0.007 | N72: con_np | O72: con_forecast_stk | P72: 同比增长率
A73: 成长 | C73: qor_acc | D73: 8期季度营业收入对时间回归的二次项系数，lm(qe~t^2+t) | E73: qor_acc | I73: 0.011 | N73: oper_rev | O73: Q | P73: 统计指标
A74: 成长 | C74: sgro3 | D74: 回归计算的最近3年复合增长率，只取年报数据。LM(总营业收入~T+1），取T的回归系数 | E74: sgro3 | I74: 0.007 | N74: tot_oper_rev | O74: RAW | P74: 同比增长率
A75: 成长 | C75: reg_con_np | D75: 来源天风，通过回归法计算企业的两年复合增长率。以最小二乘法拟合点列(1,Profit_FY0)，(2,Profit_FY1)，(3,Profit_FY2)的线性方程;同时我们添加约束条件使得回归方程通过点(1,Profit_FY0)。系数b的拟合值푏即为企业每年的净利润增长额度，将푏除以三年净利润Profit_FY0，Profit_FY1，Profit_FY2平均值即得到企业的预期复合增长率,系数可化简为b=0.4∗(fy2-fy1)+0.6∗(fy1−fy0)因此，回归系数b实质上就是企业在前后两个年度净利润增长值的加权平均，将系数除以三年的平均净利润即得到增长率Growth=b/(y0+y1+y2)/3 | E75: reg_con_np | F75: 是 | I75: 0.006 | N75: con_np | O75: con_forecast_stk | P75: 同比增长率
A76: 成长 | C76: fg2 | D76: ((NetProtif_Forecast-NetProfit)/abs(NetProfit)+1)^(1/N)-1，N=2。只用年报数据 | E76: fg | F76: 是 | I76: 0.006 | O76: RAW | P76: 同比增长率
A77: 成长 | C77: egro3 | D77: 过去3年净利润回归计算得到的增长率，年报每股净利润对时间的回归系数除以平均净利润绝对值,对因变量进行3倍中位数调整。只取年报数据 | E77: egro3 | I77: 0.004 | N77: net_profit_excl_min_int_inc | P77: 同比增长率
A78: 成长 | C78: egro5 | D78: 过去5年净利润回归计算得到的增长率，年报每股净利润对时间的回归系数除以平均净利润绝对值,对因变量进行3倍中位数调整。只取年报数据 | E78: egro5 | F78: 是 | I78: 0.004 | N78: net_profit_excl_min_int_inc | P78: 同比增长率
A79: 成长 | C79: con_npcgrate_2y_roll | D79: 滚动一致预期净利润两年符合增长率 | E79: con_forcast | I79: 0.002 | N79: con_npcgrate_2y_roll | P79: 同比增长率
A80: 成长 | C80: egibs | D80: 一致预期净利润增长率，(明年一致预期净利润均值-当年一致预期净利润均值)/abs(当年一致预期净利润均值)。 | E80: egibs | I80: -0.01 | N80: con_np | O80: con_forecast_stk | P80: 同比增长率
A81: 分析师 | B81: cov | C81: cvg_og1 | D81: 1个月覆盖度,机构数 | E81: cvg_og | F81: 否 | G81: 优化 | I81: 0.035 | J81: 0.036 | K81: 对1-4个月进行遍历，从覆盖度和表现上目前3个月合理。替代cvg
A82: 分析师 | B82: cov | C82: cvg_og2 | D82: 2个月覆盖度,机构数 | E82: cvg_og | F82: 否 | G82: 优化 | I82: 0.043 | J82: 0.044 | K82: 对1-4个月进行遍历，从覆盖度和表现上目前3个月合理。替代cvg
A83: 分析师 | B83: cov | C83: cvg_og3 | D83: 3个月覆盖度,机构数 | E83: cvg_og | F83: 是 | G83: 优化 | I83: 0.046 | J83: 0.046 | K83: 对1-4个月进行遍历，从覆盖度和表现上目前3个月合理。替代cvg
A84: 分析师 | B84: cov | C84: cvg1 | D84: n个月覆盖度（同一机构不同日期算多次） | E84: cvg | F84: NA | G84: 删除 | I84: 0.035 | J84: NA | K84: 可以使用cvg_og，只考虑机构数，表现也更好一些。
A85: 分析师 | B85: cov | C85: cvg2 | D85: n个月覆盖度（同一机构不同日期算多次） | E85: cvg | F85: NA | G85: 删除 | I85: 0.043 | J85: NA | K85: 可以使用cvg_og，只考虑机构数，表现也更好一些。
A86: 分析师 | B86: cov | C86: cvg3 | D86: n个月覆盖度（同一机构不同日期算多次） | E86: cvg | F86: NA | G86: 删除 | I86: 0.046 | J86: NA | K86: 可以使用cvg_og，只考虑机构数，表现也更好一些。
A87: 分析师 | B87: dispersion | C87: eps_variability2 | D87: n个月分析师分歧度,至少3家覆盖 | E87: eps_variability | F87: 是 | G87: 不变 | I87: 0.019 | J87: NA | K87: 测试1/2/3/6/9个月
A88: 分析师 | B88: drec | C88: darec | D88: 评级变动加权（darec_l:所有机构，180工作日，60半衰期;darec: 所有机构,180工作日，30半衰期;darec_w: 所有机构，90工作日，30半衰期;darec_s） | E88: darec | F88: 是 | G88: 删除 | I88: 0.017 | J88: NA | K88: 代码合并，与darec_l相关性很高，不保存
A89: 分析师 | B89: drec | C89: darec_100_60 | D89: 代码合并，使用100工作日，半衰期60工作日，改名darec100_60。替代原先的darec和darec_l, darec和darec_l两者相关性极高,合并。 | E89: darec | F89: 是 | G89: 优化 | I89: 0.017 | J89: 0.015 | K89: 代码合并，替代darec和darec_l
A90: 分析师 | B90: drec | C90: darec_20_10 | D90: 代码合并，使用20工作日，半衰期10工作日，改名为darec20_10，与darec80_30比较。替代原先darec_w和darec_s | E90: darec | F90: 是 | G90: 优化 | I90: 0.004 | J90: 0.013 | K90: 代码合并，替代darec_s
A91: 分析师 | B91: drec | C91: darec_l | D91: 评级变动加权（darec_l:所有机构，180工作日，60半衰期;darec: 所有机构,180工作日，30半衰期;darec_w: 所有机构，90工作日，30半衰期;darec_s） | E91: darec | F91: 是 | G91: 删除 | I91: 0.018 | J91: NA | K91: 代码合并，使用100工作日，半衰期60工作日，改名darec100_60
A92: 分析师 | B92: drec | C92: darec_s | D92: 评级变动加权（darec_l:所有机构，180工作日，60半衰期;darec: 所有机构,180工作日，30半衰期;darec_w: 所有机构，90工作日，30半衰期;darec_s） | E92: darec | F92: 是 | G92: 删除 | I92: 0.004 | J92: NA | K92: 代码合并，使用20工作日，半衰期10工作日，改名为darec20_10，与darec80_30比较
A93: 分析师 | B93: drec | C93: drec | D93: 最新一致预期评级变化,这个月评级-上个月 | E93: drec | F93: 否 | G93: 不变 | I93: 0.009 | J93: NA
A94: 分析师 | B94: drec | C94: recud | D94: 评级方向加权(recud:180工作日，30半衰期;recud_l: 180工作日，60半衰期;recud_s: 180工作日，10半衰期) | E94: recud | F94: 是 | G94: 删除 | I94: 0.021 | J94: NA | K94: 代码合并,使用recud_180_30
A95: 分析师 | B95: drec | C95: recud_180_30 | D95: 评级方向加权(recud:180工作日，30半衰期;recud_l: 180工作日，60半衰期;recud_s: 180工作日，10半衰期) | E95: recud | F95: 是 | G95: 优化 | I95: 0.021 | J95: 0.02 | K95: 代码合并，替代recud和recud_l
A96: 分析师 | B96: drec | C96: recud_20_10 | D96: 评级方向加权(recud:180工作日，30半衰期;recud_l: 180工作日，60半衰期;recud_s: 180工作日，10半衰期) | E96: recud | F96: 是 | G96: 优化 | I96: 0.016 | J96: 0.013 | K96: 代码合并，替代recud_s
A97: 分析师 | B97: drec | C97: recud_l | D97: 评级方向加权(recud:180工作日，30半衰期;recud_l: 180工作日，60半衰期;recud_s: 180工作日，10半衰期) | E97: recud | F97: 是 | G97: 删除 | I97: 0.022 | J97: NA | K97: 代码合并,与recud相关性高，不保存
A98: 分析师 | B98: drec | C98: recud_s | D98: 评级方向加权(recud:180工作日，30半衰期;recud_l: 180工作日，60半衰期;recud_s: 180工作日，10半衰期) | E98: recud | F98: 是 | G98: 删除 | I98: 0.016 | J98: NA | K98: 代码合并,使用recud_20_10
A99: 分析师 | B99: drev | C99: darev | D99: 盈利预测同比变化/总市值(darev:90天，30半衰期;darev_l: 120天，60半衰期;darev_s: 40天，10半衰期;添加darev_num_hl:num工作日内的预测，hl半衰期加权) | E99: darev | F99: NA | G99: 删除 | I99: 0.035 | J99: NA | K99: 代码合并，与darev_l相关性很高,去掉，添加darev_60_20,不做比较
A100: 分析师 | B100: drev | C100: darev_120_60 | D100: 代码合并，参数改为120工作日，半衰期60工作日，替代darev_l | E100: darev | F100: 是 | G100: 优化 | I100: 0.034 | J100: 0.034 | K100: 代码合并,替代drev_l
...

Sheet 分析师_zz800
A1: 主题 | B1: sig.name | C1: X2009 | D1: X2010 | E1: X2011 | F1: X2012 | G1: X2013 | H1: X2014 | I1: X2015 | J1: X2016 | K1: X2017 | L1: X2018 | M1: X2019 | N1: rank.ic | O1: rank.ic.ir | P1: coef.estimate | Q1: coef.ir | R1: coef.t | S1: sig.coverage | T1: cor.with.pre.period | U1: min.date | V1: max.date | W1: period.count
A2: 分析师 | B2: cvg_og1 | C2: 0.0363 | D2: 0.0716 | E2: 0.0482 | F2: 0.0382 | G2: 0.0466 | H2: -0.014 | I2: 0.0343 | J2: 0.0138 | K2: 0.0452 | L2: 0.0364 | M2: 0.0376 | N2: 0.036 | O2: 1.83 | P2: 0.002 | Q2: 1.14 | R2: 1.21 | S2: 0.999 | T2: 0.5 | U2: 20081231 | V2: 20190731 | W2: 128
A3: 分析师 | B3: cvg_og2 | C3: 0.0333 | D3: 0.0742 | E3: 0.0467 | F3: 0.0475 | G3: 0.0565 | H3: -0.0101 | I3: 0.047 | J3: 0.0186 | K3: 0.0685 | L3: 0.0461 | M3: 0.0546 | N3: 0.044 | O3: 1.92 | P3: 0.0028 | Q3: 1.35 | R3: 1.62 | S3: 0.999 | T3: 0.82 | U3: 20081231 | V3: 20190731 | W3: 128
A4: 分析师 | B4: cvg_og3 | C4: 0.0338 | D4: 0.072 | E4: 0.0462 | F4: 0.0464 | G4: 0.0584 | H4: -0.0078 | I4: 0.0529 | J4: 0.0245 | K4: 0.0767 | L4: 0.0459 | M4: 0.0611 | N4: 0.046 | O4: 1.95 | P4: 0.0032 | Q4: 1.45 | R4: 1.76 | S4: 0.999 | T4: 0.91 | U4: 20081231 | V4: 20190731 | W4: 128
A5: 分析师 | B5: cvg1 | C5: 0 | D5: 0.0709 | E5: 0.0478 | F5: 0.0367 | G5: 0.0455 | H5: -0.013 | I5: 0.0358 | J5: 0.0149 | K5: 0.0421 | L5: 0.0342 | M5: 0.038 | N5: 0.035 | O5: 1.79 | P5: 0.002 | Q5: 1.09 | R5: 1.23 | S5: 1 | T5: 0.49 | U5: 20100129 | V5: 20190731 | W5: 115
A6: 分析师 | B6: cvg2 | C6: 0 | D6: 0.0762 | E6: 0.0466 | F6: 0.0489 | G6: 0.0558 | H6: -0.0088 | I6: 0.0486 | J6: 0.0185 | K6: 0.0619 | L6: 0.0429 | M6: 0.0531 | N6: 0.044 | O6: 1.99 | P6: 0.0027 | Q6: 1.31 | R6: 1.64 | S6: 1 | T6: 0.82 | U6: 20100129 | V6: 20190731 | W6: 115
A7: 分析师 | B7: cvg3 | C7: 0 | D7: 0.0746 | E7: 0.0463 | F7: 0.0471 | G7: 0.0573 | H7: -0.0045 | I7: 0.0568 | J7: 0.024 | K7: 0.0672 | L7: 0.0428 | M7: 0.0605 | N7: 0.046 | O7: 2.05 | P7: 0.003 | Q7: 1.39 | R7: 1.76 | S7: 1 | T7: 0.9 | U7: 20100129 | V7: 20190731 | W7: 115
A8: 分析师 | B8: darec | C8: 0.021 | D8: 0.0198 | E8: 0.0153 | F8: -0.0004 | G8: 0.0286 | H8: 0.039 | I8: 0.0268 | J8: 0.0071 | K8: 0.0037 | L8: 0.0202 | M8: 0.0052 | N8: 0.017 | O8: 1.29 | P8: 0.0018 | Q8: 2.11 | R8: 0.74 | S8: 0.814 | T8: 0.61 | U8: 20081231 | V8: 20190731 | W8: 128
A9: 分析师 | B9: darec_100_60 | C9: 0.0323 | D9: 0.0393 | E9: 0.0148 | F9: 0.0063 | G9: 0.0147 | H9: 0.0045 | I9: 0.0097 | J9: -0.0002 | K9: 0.0168 | L9: 0.0158 | M9: 0.0018 | N9: 0.015 | O9: 1.3 | P9: 0.0015 | Q9: 1.45 | R9: 0.54 | S9: 0.828 | T9: 0.58 | U9: 20081231 | V9: 20190731 | W9: 128
A10: 分析师 | B10: darec_20_10 | C10: 0.0509 | D10: 0.0333 | E10: 0.0278 | F10: 0.0033 | G10: 0.0025 | H10: 0.0071 | I10: -0.0204 | J10: -0.016 | K10: 0.0051 | L10: 0.0338 | M10: 0.0183 | N10: 0.013 | O10: 0.83 | P10: 0.0016 | Q10: 1.37 | R10: 0.49 | S10: 0.598 | T10: -0.02 | U10: 20081231 | V10: 20190731 | W10: 128
A11: 分析师 | B11: darec_l | C11: 0.0193 | D11: 0.0144 | E11: 0.024 | F11: 0.001 | G11: 0.0318 | H11: 0.0312 | I11: 0.0267 | J11: 0.0102 | K11: 0.0075 | L11: 0.0201 | M11: 0.0019 | N11: 0.018 | O11: 1.39 | P11: 0.0019 | Q11: 2.1 | R11: 0.75 | S11: 0.817 | T11: 0.71 | U11: 20081231 | V11: 20190731 | W11: 128
A12: 分析师 | B12: darec_s | C12: 0.0248 | D12: 0.0292 | E12: 0.001 | F12: 0.0311 | G12: 0.0043 | H12: 0 | I12: -0.0175 | J12: -0.0247 | K12: -0.0257 | L12: 0.0428 | M12: -0.029 | N12: 0.004 | O12: 0.25 | P12: 0.0008 | Q12: 0.83 | R12: 0.27 | S12: 0.663 | T12: 0.23 | U12: 20081231 | V12: 20190731 | W12: 128
A13: 分析师 | B13: darev | C13: 0.0517 | D13: 0.0623 | E13: 0.0356 | F13: 0.0289 | G13: 0.0448 | H13: 0.0064 | I13: 0.0346 | J13: 0.0094 | K13: 0.0482 | L13: 0.0248 | M13: 0.0444 | N13: 0.035 | O13: 2.49 | P13: 0.0034 | Q13: 2.43 | R13: 1.24 | S13: 0.77 | T13: 0.65 | U13: 20081231 | V13: 20190731 | W13: 128
... A37: 分析师 | B37: revudsratio | C37: 0.0213 | D37: 0.0593 | E37: 0.035 | F37: 0.0356 | G37: 0.056 | H37: 0.0146 | I37: 0.0083 | J37: 0.0241 | K37: 0.0556 | L37: 0.0328 | M37: 0.0375 | N37: 0.034 | O37: 2.69 | P37: 0.0032 | Q37: 2.69 | R37: 1.13 | S37: 0.765 | T37: 0.65 | U37: 20081231 | V37: 20190731 | W37: 128

Sheet 成长_broad
A1: sig.name | B1: X2009 | C1: X2010 | D1: X2011 | E1: X2012 | F1: X2013 | G1: X2014 | H1: X2015 | I1: X2016 | J1: X2017 | K1: X2018 | L1: X2019 | M1: rank.ic | N1: rank.ic.ir | O1: coef.estimate | P1: coef.ir | Q1: coef.t | R1: sig.coverage | S1: cor.with.pre.period | T1: min.date | U1: max.date | V1: period.count
A2: ar_over | B2: 0.0284 | C2: 0.0325 | D2: 0.0177 | E2: 0.0383 | F2: 0.0478 | G2: 0.0208 | H2: 0.0096 | I2: 0.02 | J2: 0.0409 | K2: 0.0387 | L2: 0.0266 | M2: 0.029 | N2: 2.82 | O2: 0.0021 | P2: 2.16 | Q2: 1.06 | R2: 0.999 | S2: 0.71 | T2: 20081231 | U2: 20190731 | V2: 128
A3: ar_over1 | B3: 0.0285 | C3: 0.0295 | D3: 0.0242 | E3: 0.0407 | F3: 0.0506 | G3: 0.0229 | H3: 0.0099 | I3: 0.0255 | J3: 0.0426 | K3: 0.0544 | L3: 0.0365 | M3: 0.033 | N3: 3.01 | O3: 0.0025 | P3: 2.37 | Q3: 1.24 | R3: 0.999 | S3: 0.62 | T3: 20081231 | U3: 20190731 | V3: 128
A4: cfg_ttm | B4: 0.0125 | C4: 0.0217 | D4: 0.0227 | E4: 0.0019 | F4: 0.0305 | G4: 0.022 | H4: 0.031 | I4: 0.0209 | J4: 0.0016 | K4: 0.0282 | L4: 0.0078 | M4: 0.019 | N4: 1.8 | O4: 0.0011 | P4: 1.18 | Q4: 0.53 | R4: 0.861 | S4: 0.92 | T4: 20081231 | U4: 20190731 | V4: 128
A5: con_npcgrate_2y_roll | B5: 0.0007 | C5: 0.0359 | D5: 0.0142 | E5: 0.0225 | F5: -0.0036 | G5: -0.0171 | H5: -0.0044 | I5: -0.0368 | J5: 0.0199 | K5: -0.0212 | L5: 0.0123 | M5: 0.002 | N5: 0.13 | O5: 0.0009 | P5: 0.69 | Q5: 0.31 | R5: 0.857 | S5: 0.93 | T5: 20081231 | U5: 20190731 | V5: 128
A6: con_np_yoy_roll | B6: 0.0108 | C6: 0.018 | D6: 0.024 | E6: 0.0406 | F6: 0.0357 | G6: -0.0143 | H6: 0.0252 | I6: -0.0267 | J6: 0.0271 | K6: -0.0064 | L6: 0.0182 | M6: 0.014 | N6: 0.92 | O6: 0.0015 | P6: 1.01 | Q6: 0.59 | R6: 0.989 | S6: 0.87 | T6: 20081231 | U6: 20190731 | V6: 128
A7: con_or_yoy_roll | B7: -0.003 | C7: 0.0329 | D7: 0.0245 | E7: 0.0214 | F7: 0.0403 | G7: -0.0238 | H7: 0.0254 | I7: -0.0176 | J7: 0.0309 | K7: 0.0048 | L7: 0.0106 | M7: 0.013 | N7: 0.88 | O7: 0.0014 | P7: 0.88 | Q7: 0.62 | R7: 0.994 | S7: 0.9 | T7: 20081231 | U7: 20190731 | V7: 128
A8: con_peg_roll | B8: 0.0231 | C8: 0.0625 | D8: 0.0321 | E8: 0.0451 | F8: 0.0152 | G8: 0.0169 | H8: 0.0348 | I8: 0.0151 | J8: 0.0549 | K8: -0.0093 | L8: 0.0222 | M8: 0.029 | N8: 1.9 | O8: 0.0028 | P8: 1.74 | Q8: 0.97 | R8: 0.827 | S8: 0.91 | T8: 20081231 | U8: 20190731 | V8: 128
A9: da2a | B9: 0.0406 | C9: 0.0595 | D9: 0.0362 | E9: 0.0398 | F9: 0.0552 | G9: 0.0025 | H9: 0.0458 | I9: 0.0309 | J9: 0.0472 | K9: 0.0424 | L9: 0.0252 | M9: 0.039 | N9: 2.35 | O9: 0.002 | P9: 1.44 | Q9: 0.93 | R9: 0.999 | S9: 0.73 | T9: 20081231 | U9: 20190731 | V9: 128
A10: da2ev | B10: 0.0157 | C10: 0.0311 | D10: 0.0197 | E10: 0.0215 | F10: 0.0254 | G10: 0.0363 | H10: 0.0428 | I10: 0.0271 | J10: 0.0191 | K10: 0.0059 | L10: 0.0116 | M10: 0.024 | N10: 2.31 | O10: 0.0017 | P10: 1.54 | Q10: 0.73 | R10: 0.996 | S10: 0.92 | T10: 20081231 | U10: 20190731 | V10: 128
A11: dafc2ia | B11: 0.0526 | C11: 0.0236 | D11: 0.0075 | E11: 0.0083 | F11: 0.0308 | G11: 0.0137 | H11: 0.0304 | I11: 0.0316 | J11: 0.0181 | K11: 0.0199 | L11: 0.0033 | M11: 0.022 | N11: 1.23 | O11: 0.0009 | P11: 1.18 | Q11: 0.47 | R11: 0.922 | S11: 0.86 | T11: 20081231 | U11: 20190731 | V11: 128
A12: de2e | B12: -0.0023 | C12: 0.005 | D12: 0.0407 | E12: 0.0301 | F12: 0.0306 | G12: 0.0011 | H12: 0.0331 | I12: 0.0141 | J12: 0.0301 | K12: 0.0011 | L12: 0.0225 | M12: 0.019 | N12: 1.28 | O12: 0.0013 | P12: 0.99 | Q12: 0.6 | R12: 0.999 | S12: 0.89 | T12: 20081231 | U12: 20190731 | V12: 128
A13: de2p | B13: 0.0266 | C13: 0.067 | D13: 0.0439 | E13: 0.0449 | F13: 0.0481 | G13: 0.0261 | H13: 0.0489 | I13: 0.0293 | J13: 0.0746 | K13: 0.0411 | L13: 0.0355 | M13: 0.044 | N13: 2.89 | O13: 0.0029 | P13: 1.8 | Q13: 1.4 | R13: 0.999 | S13: 0.77 | T13: 20081231 | U13: 20190731 | V13: 128
... A87: sus | B87: 0.0132 | C87: 0.0208 | D87: 0.043 | E87: 0.0403 | F87: 0.0379 | G87: 0.011 | H87: 0.0231 | I87: 0.0153 | J87: 0.0426 | K87: 0.0322 | L87: 0.0342 | M87: 0.028 | N87: 2.96 | O87: 0.0027 | P87: 2.52 | Q87: 1.26 | R87: 0.976 | S87: 0.8 | T87: 20081231 | U87: 20190731 | V87: 128

Sheet 成长_zz800
A1: sig.name | B1: X2009 | C1: X2010 | D1: X2011 | E1: X2012 | F1: X2013 | G1: X2014 | H1: X2015 | I1: X2016 | J1: X2017 | K1: X2018 | L1: X2019 | M1: rank.ic | N1: rank.ic.ir | O1: coef.estimate | P1: coef.ir | Q1: coef.t | R1: sig.coverage | S1: cor.with.pre.period | T1: min.date | U1: max.date | V1: period.count
A2: de2p | B2: 0.0154 | C2: 0.0702 | D2: 0.0501 | E2: 0.0532 | F2: 0.031 | G2: 0.0149 | H2: 0.0508 | I2: 0.037 | J2: 0.0934 | K2: 0.0418 | L2: 0.0578 | M2: 0.047 | N2: 2.33 | O2: 0.003 | P2: 1.51 | Q2: 1.03 | R2: 0.999 | S2: 0.77 | T2: 20081231 | U2: 20190731 | V2: 128
A3: nde2p | B3: 0.0173 | C3: 0.0642 | D3: 0.0542 | E3: 0.0557 | F3: 0.0258 | G3: 0.0091 | H3: 0.0386 | I3: 0.0385 | J3: 0.0939 | K3: 0.0662 | L3: 0.0645 | M3: 0.047 | N3: 2.57 | O3: 0.0031 | P3: 1.71 | Q3: 1.08 | R3: 0.999 | S3: 0.75 | T3: 20081231 | U3: 20190731 | V3: 128
A4: ne2e_q | B4: 0.0305 | C4: 0.0693 | D4: 0.0565 | E4: 0.0501 | F4: 0.0333 | G4: 0.0072 | H4: 0.0388 | I4: 0.0349 | J4: 0.0709 | K4: 0.0623 | L4: 0.0699 | M4: 0.047 | N4: 2.56 | O4: 0.0028 | P4: 2.03 | Q4: 1.08 | R4: 0.999 | S4: 0.75 | T4: 20081231 | U4: 20190731 | V4: 128
A5: nqdroe | B5: 0.0202 | C5: 0.0569 | D5: 0.0555 | E5: 0.0546 | F5: 0.0279 | G5: 0.0144 | H5: 0.0195 | I5: 0.0354 | J5: 0.0821 | K5: 0.0609 | L5: 0.071 | M5: 0.045 | N5: 2.62 | O5: 0.0034 | P5: 1.83 | Q5: 1.06 | R5: 0.998 | S5: 0.75 | T5: 20081231 | U5: 20190731 | V5: 128
A6: qdroe | B6: 0.0246 | C6: 0.0597 | D6: 0.0478 | E6: 0.0624 | F6: 0.0306 | G6: 0.0166 | H6: 0.03 | I6: 0.0393 | J6: 0.0797 | K6: 0.0363 | L6: 0.0636 | M6: 0.044 | N6: 2.45 | O6: 0.0032 | P6: 1.72 | Q6: 1.02 | R6: 0.99 | S6: 0.78 | T6: 20081231 | U6: 20190731 | V6: 128
A7: sup_con_np_yg | B7: 0.0144 | C7: 0.0514 | D7: 0.0488 | E7: 0.0572 | F7: 0.0456 | G7: 0.0029 | H7: 0.0456 | I7: 0.0408 | J7: 0.0788 | K7: 0.0576 | L7: 0.0427 | M7: 0.044 | N7: 2.28 | O7: 0.0034 | P7: 1.81 | Q7: 0.98 | R7: 0.929 | S7: 0.82 | T7: 20081231 | U7: 20190731 | V7: 128
A8: kqdroe | B8: 0.0076 | C8: 0.0668 | D8: 0.045 | E8: 0.0499 | F8: 0.0362 | G8: 0.0148 | H8: 0.0233 | I8: 0.0443 | J8: 0.0778 | K8: 0.041 | L8: 0.0636 | M8: 0.042 | N8: 2.29 | O8: 0.0031 | P8: 1.64 | Q8: 1.01 | R8: 0.97 | S8: 0.79 | T8: 20081231 | U8: 20190731 | V8: 128
A9: sue | B9: 0.0391 | C9: 0.0573 | D9: 0.0469 | E9: 0.0468 | F9: 0.0348 | G9: 0.0229 | H9: 0.0352 | I9: 0.0402 | J9: 0.0661 | K9: 0.0336 | L9: 0.0448 | M9: 0.042 | N9: 2.8 | O9: 0.0034 | P9: 2.32 | Q9: 1.08 | R9: 0.99 | S9: 0.76 | T9: 20081231 | U9: 20190731 | V9: 128
A10: suoi | B10: 0.0218 | C10: 0.052 | D10: 0.0428 | E10: 0.0364 | F10: 0.0324 | G10: 0.0203 | H10: 0.0289 | I10: 0.0491 | J10: 0.0616 | K10: 0.0532 | L10: 0.0524 | M10: 0.041 | N10: 2.93 | O10: 0.0035 | P10: 2.49 | Q10: 1.13 | R10: 0.99 | S10: 0.77 | T10: 20081231 | U10: 20190731 | V10: 128
A11: kfes1 | B11: 0.0066 | C11: 0.065 | D11: 0.0352 | E11: 0.0432 | F11: 0.0441 | G11: 0.009 | H11: 0.0267 | I11: 0.0351 | J11: 0.0767 | K11: 0.0398 | L11: 0.07 | M11: 0.04 | N11: 2.33 | O11: 0.003 | P11: 1.63 | Q11: 0.93 | R11: 0.922 | S11: 0.81 | T11: 20081231 | U11: 20190731 | V11: 128
A12: kqdroa | B12: 0.0099 | C12: 0.051 | D12: 0.0449 | E12: 0.0452 | F12: 0.029 | G12: 0.0177 | H12: 0.0248 | I12: 0.0399 | J12: 0.0748 | K12: 0.047 | L12: 0.0684 | M12: 0.04 | N12: 2.44 | O12: 0.0032 | P12: 1.85 | Q12: 1.02 | R12: 0.99 | S12: 0.81 | T12: 20081231 | U12: 20190731 | V12: 128
A13: npegl | B13: 0.0135 | C13: 0.0717 | D13: 0.0512 | E13: 0.0562 | F13: 0.0048 | G13: 0.0074 | H13: 0.0822 | I13: 0.0566 | J13: 0.0727 | K13: -0.004 | L13: 0.0193 | M13: 0.04 | N13: 1.91 | O13: 0.0029 | P13: 1.48 | Q13: 0.87 | R13: 0.896 | S13: 0.88 | T13: 20081231 | U13: 20190731 | V13: 128
... A79: egibs | B79: -0.0151 | C79: -0.0168 | D79: 0.0082 | E79: -0.0036 | F79: -0.0084 | G79: -0.0087 | H79: -0.031 | I79: -0.0266 | J79: -0.0098 | K79: 0.0085 | L79: 0.0513 | M79: -0.006 | N79: -0.4 | O79: -0.0006 | P79: -0.37 | Q79: -0.1 | R79: 0.892 | S79: 0.84 | T79: 20081231 | U79: 20190731 | V79: 128

Sheet 价值因子_broad
A1: sig.name | B1: X2009 | C1: X2010 | D1: X2011 | E1: X2012 | F1: X2013 | G1: X2014 | H1: X2015 | I1: X2016 | J1: X2017 | K1: X2018 | L1: X2019 | M1: rank.ic | N1: rank.ic.ir | O1: coef.estimate | P1: coef.ir | Q1: coef.t | R1: sig.coverage | S1: cor.with.pre.period | T1: min.date | U1: max.date | V1: period.count
A2: aeb2ev | B2: 0.0293 | C2: 0.0276 | D2: 0.0285 | E2: 0.0224 | F2: 0.0131 | G2: 0.0341 | H2: 0.0223 | I2: 0.0445 | J2: 0.0319 | K2: 0.0402 | L2: 0.025 | M2: 0.029 | N2: 2.47 | O2: 0.0022 | P2: 1.57 | Q2: 1.04 | R2: 0.905 | S2: 0.94 | T2: 20081231 | U2: 20190731 | V2: 128
A3: b2p | B3: 0.0582 | C3: -0.0045 | D3: 0.0441 | E3: 0.0353 | F3: 0.0114 | G3: 0.0985 | H3: 0.0237 | I3: 0.0977 | J3: 0.054 | K3: 0.0449 | L3: 0.0392 | M3: 0.046 | N3: 1.73 | O3: 0.0027 | P3: 0.81 | Q3: 1.24 | R3: 0.999 | S3: 0.97 | T3: 20081231 | U3: 20190731 | V3: 128
A4: b2paddcor20 | B4: 0 | C4: 0.0159 | D4: 0.0848 | E4: 0.0579 | F4: 0.036 | G4: 0.0879 | H4: 0.0446 | I4: 0.1207 | J4: 0.0896 | K4: 0.0823 | L4: 0.0737 | M4: 0.069 | N4: 2.94 | O4: 0.004 | P4: 1.46 | Q4: 2.05 | R4: 0.98 | S4: 0.59 | T4: 20091231 | U4: 20190731 | V4: 116
A5: cfo2ev | B5: 0.0389 | C5: 0.0316 | D5: 0.0339 | E5: 0.0195 | F5: 0.0228 | G5: 0.0467 | H5: 0.0281 | I5: 0.066 | J5: 0.0422 | K5: 0.0466 | L5: 0.0334 | M5: 0.037 | N5: 2.71 | O5: 0.0025 | P5: 1.44 | Q5: 1.18 | R5: 0.912 | S5: 0.94 | T5: 20081231 | U5: 20190731 | V5: 128
A6: cfo2p | B6: 0.0332 | C6: 0.0169 | D6: 0.0258 | E6: 0.0114 | F6: 0.0196 | G6: 0.0435 | H6: 0.0323 | I6: 0.0607 | J6: 0.0331 | K6: 0.0388 | L6: 0.0292 | M6: 0.031 | N6: 2.59 | O6: 0.0016 | P6: 1.21 | Q6: 0.81 | R6: 0.999 | S6: 0.93 | T6: 20081231 | U6: 20190731 | V6: 128
A7: con_pb_roll | B7: 0.0688 | C7: 0.0051 | D7: 0.0488 | E7: 0.043 | F7: 0.0145 | G7: 0.0987 | H7: 0.0317 | I7: 0.0987 | J7: 0.0634 | K7: 0.0436 | L7: 0.036 | M7: 0.051 | N7: 1.94 | O7: 0.0032 | P7: 0.96 | Q7: 1.42 | R7: 0.999 | S7: 0.97 | T7: 20081231 | U7: 20190731 | V7: 128
A8: con_pe_roll | B8: 0.0602 | C8: 0.0539 | D8: 0.0491 | E8: 0.0609 | F8: 0.0431 | G8: 0.0563 | H8: 0.0692 | I8: 0.0946 | J8: 0.0906 | K8: 0.027 | L8: 0.023 | M8: 0.058 | N8: 3.05 | O8: 0.0045 | P8: 1.87 | Q8: 1.94 | R8: 0.999 | S8: 0.94 | T8: 20081231 | U8: 20190731 | V8: 128
A9: con_ps_roll | B9: 0.032 | C9: -0.0036 | D9: 0.0188 | E9: 0.0188 | F9: -0.0074 | G9: 0.0698 | H9: 0.0146 | I9: 0.064 | J9: 0.0418 | K9: 0.0171 | L9: 0.0239 | M9: 0.026 | N9: 1.26 | O9: 0.002 | P9: 0.79 | Q9: 0.91 | R9: 0.999 | S9: 0.98 | T9: 20081231 | U9: 20190731 | V9: 128
A10: d2p | B10: 0.0155 | C10: 0.0396 | D10: 0.0258 | E10: 0.0112 | F10: 0.0469 | G10: 0.0556 | H10: 0.0559 | I10: 0.0668 | J10: 0.0369 | K10: 0.0622 | L10: 0.0421 | M10: 0.042 | N10: 2.95 | O10: 0.0025 | P10: 1.54 | Q10: 1.27 | R10: 0.999 | S10: 0.94 | T10: 20081231 | U10: 20190731 | V10: 128
A11: e2p | B11: 0.0368 | C11: 0.0368 | D11: 0.0531 | E11: 0.0519 | F11: 0.0445 | G11: 0.053 | H11: 0.0616 | I11: 0.082 | J11: 0.0766 | K11: 0.0457 | L11: 0.0272 | M11: 0.053 | N11: 2.82 | O11: 0.0033 | P11: 1.54 | Q11: 1.55 | R11: 0.999 | S11: 0.95 | T11: 20081231 | U11: 20190731 | V11: 128
A12: fy12p | B12: 0.0737 | C12: 0.0503 | D12: 0.051 | E12: 0.0612 | F12: 0.029 | G12: 0.0679 | H12: 0.0738 | I12: 0.0929 | J12: 0.0859 | K12: 0.0203 | L12: 0.0123 | M12: 0.058 | N12: 2.66 | O12: 0.0045 | P12: 1.66 | Q12: 1.78 | R12: 0.797 | S12: 0.94 | T12: 20081231 | U12: 20190731 | V12: 128
A13: fy23p | B13: 0.0668 | C13: 0.0487 | D13: 0.0522 | E13: 0.0668 | F13: 0.0312 | G13: 0.0647 | H13: 0.0741 | I13: 0.0928 | J13: 0.0886 | K13: 0.0192 | L13: 0.0179 | M13: 0.058 | N13: 2.73 | O13: 0.0047 | P13: 1.77 | Q13: 1.85 | R13: 0.798 | S13: 0.93 | T13: 20081231 | U13: 20190731 | V13: 128
... A24: ta2ev | B24: 0.0602 | C24: 0.0079 | D24: 0.0351 | E24: 0.0357 | F24: -0.0132 | G24: 0.0978 | H24: 0.0149 | I24: 0.0852 | J24: 0.0417 | K24: 0.0348 | L24: 0.0284 | M24: 0.039 | N24: 1.39 | O24: 0.0026 | P24: 0.84 | Q24: 1.2 | R24: 0.999 | S24: 0.98 | T24: 20081231 | U24: 20190731 | V24: 128

Sheet 价值_zz800
A1: sig.name | B1: X2009 | C1: X2010 | D1: X2011 | E1: X2012 | F1: X2013 | G1: X2014 | H1: X2015 | I1: X2016 | J1: X2017 | K1: X2018 | L1: X2019 | M1: rank.ic | N1: rank.ic.ir | O1: coef.estimate | P1: coef.ir | Q1: coef.t | R1: sig.coverage | S1: cor.with.pre.period | T1: min.date | U1: max.date | V1: period.count
A2: aeb2ev | B2: 0.0381 | C2: 0.0252 | D2: 0.0272 | E2: 0.0204 | F2: 0.0046 | G2: 0.0341 | H2: 0.0297 | I2: 0.0563 | J2: 0.0518 | K2: 0.0628 | L2: 0.0093 | M2: 0.033 | N2: 1.93 | O2: 0.0023 | P2: 1.31 | Q2: 0.76 | R2: 0.861 | S2: 0.94 | T2: 20081231 | U2: 20190731 | V2: 128
A3: b2p | B3: 0.0662 | C3: -0.0117 | D3: 0.0353 | E3: 0.0424 | F3: 0.0001 | G3: 0.1263 | H3: 0.0274 | I3: 0.107 | J3: 0.009 | K3: 0.0255 | L3: -0.0265 | M3: 0.038 | N3: 1.16 | O3: 0.0023 | P3: 0.66 | Q3: 0.68 | R3: 0.999 | S3: 0.97 | T3: 20081231 | U3: 20190731 | V3: 128
A4: b2paddcor20 | B4: 0 | C4: 0.005 | D4: 0.0721 | E4: 0.0564 | F4: 0.0389 | G4: 0.1136 | H4: 0.0578 | I4: 0.1253 | J4: 0.0254 | K4: 0.0394 | L4: -0.0044 | M4: 0.055 | N4: 2 | O4: 0.003 | P4: 1.06 | Q4: 0.97 | R4: 0.985 | S4: 0.59 | T4: 20091231 | U4: 20190731 | V4: 116
A5: cfo2ev | B5: 0.0451 | C5: 0.0292 | D5: 0.0341 | E5: 0.0204 | F5: 0.0119 | G5: 0.057 | H5: 0.0252 | I5: 0.0802 | J5: 0.0427 | K5: 0.0483 | L5: 0.0153 | M5: 0.038 | N5: 2.1 | O5: 0.0024 | P5: 1.19 | Q5: 0.79 | R5: 0.87 | S5: 0.94 | T5: 20081231 | U5: 20190731 | V5: 128
A6: cfo2p | B6: 0.0377 | C6: 0.017 | D6: 0.0231 | E6: 0.0094 | F6: 0.0085 | G6: 0.0457 | H6: 0.0336 | I6: 0.074 | J6: 0.0289 | K6: 0.0381 | L6: 0.008 | M6: 0.03 | N6: 1.88 | O6: 0.0013 | P6: 0.96 | Q6: 0.49 | R6: 0.999 | S6: 0.93 | T6: 20081231 | U6: 20190731 | V6: 128
A7: con_pb_roll | B7: 0.0797 | C7: -0.0071 | D7: 0.0422 | E7: 0.0511 | F7: 0.0007 | G7: 0.1257 | H7: 0.0378 | I7: 0.1128 | J7: 0.0201 | K7: 0.022 | L7: -0.0369 | M7: 0.043 | N7: 1.29 | O7: 0.0028 | P7: 0.78 | Q7: 0.8 | R7: 0.999 | S7: 0.97 | T7: 20081231 | U7: 20190731 | V7: 128
A8: con_pe_roll | B8: 0.0692 | C8: 0.0488 | D8: 0.0527 | E8: 0.0758 | F8: 0.0189 | G8: 0.0647 | H8: 0.0816 | I8: 0.1146 | J8: 0.0886 | K8: 0.0025 | L8: -0.0407 | M8: 0.055 | N8: 2.01 | O8: 0.0041 | P8: 1.41 | Q8: 1.25 | R8: 0.999 | S8: 0.94 | T8: 20081231 | U8: 20190731 | V8: 128
A9: con_ps_roll | B9: 0.0346 | C9: -0.015 | D9: 0.0139 | E9: 0.019 | F9: -0.0208 | G9: 0.0823 | H9: 0.0176 | I9: 0.0724 | J9: 0.0335 | K9: 0.004 | L9: -0.0349 | M9: 0.02 | N9: 0.77 | O9: 0.0018 | P9: 0.67 | Q9: 0.52 | R9: 0.999 | S9: 0.98 | T9: 20081231 | U9: 20190731 | V9: 128
A10: d2p | B10: 0.0156 | C10: 0.0281 | D10: 0.0202 | E10: 0.026 | F10: 0.0243 | G10: 0.0566 | H10: 0.0544 | I10: 0.0729 | J10: 0.0526 | K10: 0.0649 | L10: 0.0165 | M10: 0.04 | N10: 2.26 | O10: 0.0022 | P10: 1.29 | Q10: 0.76 | R10: 0.999 | S10: 0.94 | T10: 20081231 | U10: 20190731 | V10: 128
A11: e2p | B11: 0.0375 | C11: 0.0312 | D11: 0.0587 | E11: 0.0651 | F11: 0.0125 | G11: 0.0542 | H11: 0.073 | I11: 0.0963 | J11: 0.0891 | K11: 0.0372 | L11: -0.0153 | M11: 0.051 | N11: 1.96 | O11: 0.0031 | P11: 1.21 | Q11: 0.99 | R11: 0.999 | S11: 0.95 | T11: 20081231 | U11: 20190731 | V11: 128
A12: fy12p | B12: 0.0819 | C12: 0.0454 | D12: 0.0568 | E12: 0.0748 | F12: 0.0132 | G12: 0.0725 | H12: 0.0852 | I12: 0.1064 | J12: 0.0906 | K12: -0.0012 | L12: -0.0176 | M12: 0.058 | N12: 2.06 | O12: 0.0042 | P12: 1.44 | Q12: 1.26 | R12: 0.905 | S12: 0.94 | T12: 20081231 | U12: 20190731 | V12: 128
A13: fy23p | B13: 0.0773 | C13: 0.0368 | D13: 0.0603 | E13: 0.0764 | F13: 0.0118 | G13: 0.071 | H13: 0.0894 | I13: 0.1074 | J13: 0.0854 | K13: -0.0026 | L13: -0.0093 | M13: 0.057 | N13: 2.09 | O13: 0.0044 | P13: 1.48 | Q13: 1.28 | R13: 0.905 | S13: 0.93 | T13: 20081231 | U13: 20190731 | V13: 128
... A24: ta2ev | B24: 0.0667 | C24: 0.0059 | D24: 0.0315 | E24: 0.0329 | F24: -0.0273 | G24: 0.1139 | H24: 0.0198 | I24: 0.0887 | J24: 0.0158 | K24: 0.0128 | L24: -0.0356 | M24: 0.032 | N24: 0.95 | O24: 0.0023 | P24: 0.79 | Q24: 0.72 | R24: 0.999 | S24: 0.98 | T24: 20081231 | U24: 20190731 | V24: 128

Sheet 反转因子_broad
A1: sig.name | B1: X2009 | C1: X2010 | D1: X2011 | E1: X2012 | F1: X2013 | G1: X2014 | H1: X2015 | I1: X2016 | J1: X2017 | K1: X2018 | L1: X2019 | M1: rank.ic | N1: rank.ic.ir | O1: coef.estimate | P1: coef.ir | Q1: coef.t | R1: sig.coverage | S1: cor.with.pre.period | T1: min.date | U1: max.date | V1: period.count
A2: astd12m | B2: -0.0406 | C2: -0.0129 | D2: -0.0171 | E2: -0.0118 | F2: 0.0142 | G2: -0.0364 | H2: -0.0462 | I2: -0.0182 | J2: 0.0399 | K2: 0.0188 | L2: 0.031 | M2: -0.008 | N2: -0.39 | O2: 0.0006 | P2: 0.52 | Q2: 0.32 | R2: 0.956 | S2: 0.98 | T2: 20081231 | U2: 20190731 | V2: 128
A3: astd1m | B3: -0.0224 | C3: -0.0015 | D3: 0.0122 | E3: 0.0161 | F3: 0.0331 | G3: -0.0062 | H3: -0.0132 | I3: 0.0351 | J3: 0.069 | K3: 0.0308 | L3: 0.0409 | M3: 0.017 | N3: 0.82 | O3: 0.002 | P3: 1.56 | Q3: 1.17 | R3: 0.95 | S3: 0.87 | T3: 20081231 | U3: 20190731 | V3: 128
A4: astd24m | B4: -0.0558 | C4: -0.0186 | D4: -0.0163 | E4: -0.0183 | F4: 0.0156 | G4: -0.0457 | H4: -0.0501 | I4: -0.0559 | J4: 0.0357 | K4: 0.0163 | L4: 0.016 | M4: -0.017 | N4: -0.76 | O4: 0.0002 | P4: 0.15 | Q4: 0.1 | R4: 0.947 | S4: 0.99 | T4: 20081231 | U4: 20190731 | V4: 128
A5: astd3m | B5: -0.0341 | C5: -0.0136 | D5: -0.0031 | E5: 0.0104 | F5: 0.0236 | G5: -0.0223 | H5: -0.0315 | I5: 0.0233 | J5: 0.0578 | K5: 0.0266 | L5: 0.0314 | M5: 0.005 | N5: 0.25 | O5: 0.0013 | P5: 1.09 | Q5: 0.77 | R5: 0.948 | S5: 0.96 | T5: 20081231 | U5: 20190731 | V5: 128
A6: astd6m | B6: -0.0388 | C6: -0.0126 | D6: -0.0127 | E6: -0.003 | F6: 0.0144 | G6: -0.0339 | H6: -0.0411 | I6: 0.0162 | J6: 0.0483 | K6: 0.021 | L6: 0.0362 | M6: -0.002 | N6: -0.08 | O6: 0.0008 | P6: 0.75 | Q6: 0.5 | R6: 0.946 | S6: 0.98 | T6: 20081231 | U6: 20190731 | V6: 128
A7: cthl12m | B7: 0.0136 | C7: 0.0089 | D7: 0.0223 | E7: 0.0292 | F7: 0.0498 | G7: 0.009 | H7: 0.0072 | I7: 0.0029 | J7: 0.0483 | K7: 0.0321 | L7: 0.036 | M7: 0.023 | N7: 1.91 | O7: 0.0017 | P7: 1.34 | Q7: 0.79 | R7: 0.953 | S7: 0.95 | T7: 20081231 | U7: 20190731 | V7: 128
A8: cthl24m | B8: 0.0149 | C8: -0.0011 | D8: 0.0081 | E8: 0.0211 | F8: 0.0475 | G8: 0.0159 | H8: 0.0129 | I8: 0.012 | J8: 0.0395 | K8: 0.0143 | L8: 0.0236 | M8: 0.019 | N8: 1.61 | O8: 0.0013 | P8: 1.1 | Q8: 0.55 | R8: 0.944 | S8: 0.98 | T8: 20081231 | U8: 20190731 | V8: 128
A9: cthl6m | B9: -0.0021 | C9: 0.0171 | D9: 0.0319 | E9: 0.0229 | F9: 0.0481 | G9: 0.0028 | H9: 0.0068 | I9: 0.0199 | J9: 0.0484 | K9: 0.0351 | L9: 0.0474 | M9: 0.025 | N9: 1.8 | O9: 0.002 | P9: 1.45 | Q9: 0.97 | R9: 0.946 | S9: 0.86 | T9: 20081231 | U9: 20190731 | V9: 128
A10: cthl9m | B10: 0.0073 | C10: 0.0127 | D10: 0.0269 | E10: 0.0252 | F10: 0.0484 | G10: 0.015 | H10: 0.0052 | I10: 0.005 | J10: 0.0489 | K10: 0.0333 | L10: 0.0424 | M10: 0.024 | N10: 1.88 | O10: 0.0017 | P10: 1.36 | Q10: 0.85 | R10: 0.946 | S10: 0.92 | T10: 20081231 | U10: 20190731 | V10: 128
A11: cto12m | B11: 0.0094 | C11: 0.0086 | D11: 0.0317 | E11: 0.0239 | F11: 0.0366 | G11: 0.0241 | H11: 0.0213 | I11: 0.0188 | J11: 0.0433 | K11: 0.0336 | L11: 0.033 | M11: 0.026 | N11: 2.19 | O11: 0.0017 | P11: 1.4 | Q11: 0.77 | R11: 0.953 | S11: 0.94 | T11: 20081231 | U11: 20190731 | V11: 128
A12: cto24m | B12: 0.0133 | C12: -0.0077 | D12: 0.0178 | E12: 0.0197 | F12: 0.0393 | G12: 0.025 | H12: 0.0162 | I12: 0.014 | J12: 0.0404 | K12: 0.0178 | L12: 0.019 | M12: 0.02 | N12: 1.59 | O12: 0.0012 | P12: 1.03 | Q12: 0.51 | R12: 0.944 | S12: 0.97 | T12: 20081231 | U12: 20190731 | V12: 128
A13: cto6m | B13: 0.0019 | C13: 0.0147 | D13: 0.0389 | E13: 0.0241 | F13: 0.0355 | G13: 0.01 | H13: 0.0201 | I13: 0.0377 | J13: 0.0383 | K13: 0.0361 | L13: 0.0445 | M13: 0.027 | N13: 1.96 | O13: 0.0019 | P13: 1.42 | Q13: 0.93 | R13: 0.946 | S13: 0.86 | T13: 20081231 | U13: 20190731 | V13: 128
... A130: volume_volatility6m | B130: -0.011 | C130: 0.0204 | D130: 0.016 | E130: 0.0347 | F130: 0.0513 | G130: -0.0223 | H130: -0.0316 | I130: 0.0224 | J130: 0.0675 | K130: 0.0427 | L130: 0.0411 | M130: 0.02 | N130: 0.84 | O130: 0.0019 | P130: 0.96 | Q130: 1.25 | R130: 0.946 | S130: 0.96 | T130: 20081231 | U130: 20190731 | V130: 128

Sheet 反转因子_zz800
A1: sig.name | B1: X2009 | C1: X2010 | D1: X2011 | E1: X2012 | F1: X2013 | G1: X2014 | H1: X2015 | I1: X2016 | J1: X2017 | K1: X2018 | L1: X2019 | M1: rank.ic | N1: rank.ic.ir | O1: coef.estimate | P1: coef.ir | Q1: coef.t | R1: sig.coverage | S1: cor.with.pre.period | T1: min.date | U1: max.date | V1: period.count
A2: vol_freeshr | B2: 0.1108 | C2: 0.0543 | D2: 0.0731 | E2: 0.0641 | F2: 0.058 | G2: 0.1022 | H2: 0.1051 | I2: 0.1328 | J2: 0.0404 | K2: 0.0329 | L2: 0.0288 | M2: 0.074 | N2: 3 | O2: 0.0067 | P2: 2.17 | Q2: 1.73 | R2: 0.972 | S2: 0.81 | T2: 20081231 | U2: 20190731 | V2: 128
A3: i_volatility | B3: 0.0754 | C3: 0.0505 | D3: 0.0751 | E3: 0.0559 | F3: 0.0599 | G3: 0.1166 | H3: 0.1115 | I3: 0.1316 | J3: 0.0274 | K3: 0.0304 | L3: 0.0197 | M3: 0.07 | N3: 2.79 | O3: 0.0045 | P3: 1.68 | Q3: 1.22 | R3: 0.999 | S3: 0.38 | T3: 20081231 | U3: 20190731 | V3: 128
A4: ivo | B4: 0.0878 | C4: 0.0538 | D4: 0.0772 | E4: 0.0585 | F4: 0.0654 | G4: 0.1138 | H4: 0.1123 | I4: 0.1259 | J4: 0.032 | K4: 0.0302 | L4: 0.0187 | M4: 0.072 | N4: 2.93 | O4: 0.0044 | P4: 1.71 | Q4: 1.24 | R4: 0.98 | S4: 0.39 | T4: 20081231 | U4: 20190731 | V4: 128
A5: ivo_ff12m | B5: 0.055 | C5: 0.0203 | D5: 0.0493 | E5: 0.0349 | F5: 0.046 | G5: 0.1074 | H5: 0.0561 | I5: 0.1132 | J5: 0.0368 | K5: 0.0669 | L5: 0.0107 | M5: 0.056 | N5: 2.03 | O5: 0.0037 | P5: 1.18 | Q5: 0.99 | R5: 0.999 | S5: 0.97 | T5: 20081231 | U5: 20190731 | V5: 128
A6: ivo_ff1m | B6: 0.0886 | C6: 0.055 | D6: 0.0796 | E6: 0.0584 | F6: 0.0671 | G6: 0.1132 | H6: 0.1093 | I6: 0.1261 | J6: 0.0302 | K6: 0.0291 | L6: 0.0192 | M6: 0.072 | N6: 2.91 | O6: 0.0044 | P6: 1.7 | Q6: 1.24 | R6: 0.979 | S6: 0.39 | T6: 20081231 | U6: 20190731 | V6: 128
A7: ivo_ff24m | B7: 0.037 | C7: 0.004 | D7: 0.0453 | E7: 0.031 | F7: 0.0378 | G7: 0.1014 | H7: 0.0259 | I7: 0.101 | J7: 0.062 | K7: 0.0545 | L7: 0.0184 | M7: 0.048 | N7: 1.93 | O7: 0.0031 | P7: 1.01 | Q7: 0.82 | R7: 0.999 | S7: 0.99 | T7: 20081231 | U7: 20190731 | V7: 128
A8: ivo_ff3m | B8: 0.0552 | C8: 0.0302 | D8: 0.0752 | E8: 0.0579 | F8: 0.053 | G8: 0.1104 | H8: 0.1042 | I8: 0.151 | J8: 0.0262 | K8: 0.0505 | L8: 0.0191 | M8: 0.068 | N8: 2.37 | O8: 0.0042 | P8: 1.42 | Q8: 1.17 | R8: 0.992 | S8: 0.82 | T8: 20081231 | U8: 20190731 | V8: 128
A9: ivo_ff6m | B9: 0.0487 | C9: 0.0291 | D9: 0.058 | E9: 0.0444 | F9: 0.0513 | G9: 0.1101 | H9: 0.066 | I9: 0.1383 | J9: 0.0267 | K9: 0.059 | L9: 0.0108 | M9: 0.06 | N9: 2.08 | O9: 0.0038 | P9: 1.2 | Q9: 1.08 | R9: 0.998 | S9: 0.92 | T9: 20081231 | U9: 20190731 | V9: 128
A10: ivr | B10: 0.0892 | C10: 0.0488 | D10: 0.059 | E10: 0.0523 | F10: 0.0656 | G10: 0.0915 | H10: 0.0925 | I10: 0.0901 | J10: 0.0343 | K10: 0.0249 | L10: 0.0258 | M10: 0.062 | N10: 3.27 | O10: 0.0034 | P10: 1.96 | Q10: 1 | R10: 0.98 | S10: 0.23 | T10: 20081231 | U10: 20190731 | V10: 128
A11: turnover1m | B11: 0.0936 | C11: 0.0438 | D11: 0.0618 | E11: 0.043 | F11: 0.0552 | G11: 0.0881 | H11: 0.0978 | I11: 0.1132 | J11: 0.0257 | K11: 0.0256 | L11: 0.0332 | M11: 0.063 | N11: 2.99 | O11: 0.006 | P11: 2.29 | Q11: 1.49 | R11: 0.963 | S11: 0.75 | T11: 20081231 | U11: 20190731 | V11: 128
A12: turnover_amount1m | B12: 0.0935 | C12: 0.0438 | D12: 0.0616 | E12: 0.043 | F12: 0.055 | G12: 0.0879 | H12: 0.0973 | I12: 0.1131 | J12: 0.0256 | K12: 0.0256 | L12: 0.0332 | M12: 0.063 | N12: 2.99 | O12: 0.006 | P12: 2.29 | Q12: 1.49 | R12: 0.963 | S12: 0.75 | T12: 20081231 | U12: 20190731 | V12: 128
A13: vol | B13: 0.0906 | C13: 0.0392 | D13: 0.0634 | E13: 0.0442 | F13: 0.0525 | G13: 0.0874 | H13: 0.0904 | I13: 0.1171 | J13: 0.0252 | K13: 0.039 | L13: 0.0354 | M13: 0.063 | N13: 2.95 | O13: 0.006 | P13: 2.29 | Q13: 1.49 | R13: 0.972 | S13: 0.85 | T13: 20081231 | U13: 20190731 | V13: 128
... A130: highlow1m | B130: -0.0642 | C130: 0.0034 | D130: -0.0147 | E130: -0.0025 | F130: -0.0263 | G130: -0.085 | H130: -0.0416 | I130: -0.0746 | J130: 0.013 | K130: 0.007 | L130: -0.0314 | M130: -0.029 | N130: -1.07 | O130: -0.0018 | P130: -0.59 | Q130: -0.45 | R130: 0.963 | S130: 0.25 | T130: 20081231 | U130: 20190731 | V130: 128

Sheet 质量因子_broad
A1: sig.name | B1: X2009 | C1: X2010 | D1: X2011 | E1: X2012 | F1: X2013 | G1: X2014 | H1: X2015 | I1: X2016 | J1: X2017 | K1: X2018 | L1: X2019 | M1: rank.ic | N1: rank.ic.ir | O1: coef.estimate | P1: coef.ir | Q1: coef.t | R1: sig.coverage | S1: cor.with.pre.period | T1: min.date | U1: max.date | V1: period.count
A2: abacc | B2: 0.0171 | C2: 0.0003 | D2: 0.0099 | E2: 0.0039 | F2: 0.0111 | G2: 0.0213 | H2: 0.0093 | I2: 0.0163 | J2: -0.0017 | K2: 0.0187 | L2: 0.0218 | M2: 0.011 | N2: 1.13 | O2: 0.0013 | P2: 1.27 | Q2: 0.58 | R2: 0.842 | S2: 0.91 | T2: 20081231 | U2: 20190731 | V2: 128
A3: abaccall | B3: 0.0146 | C3: -0.0062 | D3: 0.0086 | E3: 0.0058 | F3: 0.0079 | G3: 0.0192 | H3: -0.0011 | I3: 0.0062 | J3: -0.0044 | K3: 0.01 | L3: 0.02 | M3: 0.007 | N3: 0.67 | O3: 0.001 | P3: 1.04 | Q3: 0.47 | R3: 0.979 | S3: 0.93 | T3: 20081231 | U3: 20190731 | V3: 128
A4: acc1 | B4: 0.0093 | C4: -0.0001 | D4: 0.0058 | E4: -0.0013 | F4: 0.0007 | G4: 0.0228 | H4: -0.0023 | I4: 0.0189 | J4: 0.0067 | K4: 0.0267 | L4: 0.0298 | M4: 0.01 | N4: 0.86 | O4: 0.001 | P4: 0.82 | Q4: 0.5 | R4: 0.857 | S4: 0.94 | T4: 20081231 | U4: 20190731 | V4: 128
A5: acca | B5: 0.016 | C5: -0.0022 | D5: 0.0027 | E5: -0.0057 | F5: -0.0052 | G5: 0.0195 | H5: -0.005 | I5: 0.0161 | J5: 0.0091 | K5: 0.0225 | L5: 0.0224 | M5: 0.008 | N5: 0.66 | O5: 0.0008 | P5: 0.69 | Q5: 0.41 | R5: 0.999 | S5: 0.93 | T5: 20081231 | U5: 20190731 | V5: 128
A6: bab | B6: 0.0372 | C6: 0.0495 | D6: 0.0517 | E6: 0.0399 | F6: 0.058 | G6: 0.0668 | H6: 0.0372 | I6: 0.0262 | J6: 0.0313 | K6: 0.0326 | L6: 0.018 | M6: 0.041 | N6: 2.66 | O6: 0.0024 | P6: 1.62 | Q6: 0.91 | R6: 0.772 | S6: 0.95 | T6: 20081231 | U6: 20190731 | V6: 128
A7: ccr | B7: 0.0254 | C7: 0.0152 | D7: 0.0123 | E7: 0.014 | F7: 0.0228 | G7: 0.0005 | H7: 0.0253 | I7: 0.0291 | J7: 0.0226 | K7: 0.0429 | L7: 0.0275 | M7: 0.021 | N7: 1.86 | O7: 0.0016 | P7: 1.19 | Q7: 0.77 | R7: 0.977 | S7: 0.95 | T7: 20081231 | U7: 20190731 | V7: 128
A8: ccrd | B8: 0.0112 | C8: -0.005 | D8: 0.0156 | E8: -0.006 | F8: 0.0155 | G8: 0.0067 | H8: 0.0108 | I8: 0.0014 | J8: 0.0191 | K8: -0.001 | L8: 0.014 | M8: 0.007 | N8: 0.93 | O8: 0.0007 | P8: 0.89 | Q8: 0.28 | R8: 0.961 | S8: 0.87 | T8: 20081231 | U8: 20190731 | V8: 128
A9: cd2d | B9: -0.0047 | C9: 0.0082 | D9: 0.0038 | E9: -0.0029 | F9: 0.0171 | G9: -0.0147 | H9: 0.0108 | I9: -0.0091 | J9: -0.0072 | K9: -0.0017 | L9: 0.001 | M9: 0 | N9: 0 | O9: 0.0005 | P9: 0.48 | Q9: 0.28 | R9: 0.978 | S9: 0.98 | T9: 20081231 | U9: 20190731 | V9: 128
A10: cfovol2a | B10: -0.0038 | C10: 0.0031 | D10: -0.0038 | E10: 0.009 | F10: -0.0015 | G10: -0.0212 | H10: -0.0019 | I10: -0.0098 | J10: 0.0035 | K10: -0.023 | L10: -0.0001 | M10: -0.005 | N10: -0.44 | O10: 0 | P10: -0.02 | Q10: -0.06 | R10: 0.997 | S10: 0.97 | T10: 20081231 | U10: 20190731 | V10: 128
A11: cr | B11: 0.0039 | C11: -0.0057 | D11: 0.0106 | E11: 0.0153 | F11: 0.0097 | G11: -0.0206 | H11: 0.003 | I11: -0.0016 | J11: -0.0153 | K11: 0.0174 | L11: 0.0027 | M11: 0.002 | N11: 0.14 | O11: 0.0004 | P11: 0.3 | Q11: 0.19 | R11: 0.978 | S11: 0.97 | T11: 20081231 | U11: 20190731 | V11: 128
A12: crd | B12: -0.0102 | C12: 0.0171 | D12: 0.0212 | E12: 0.0128 | F12: 0.0031 | G12: -0.0104 | H12: -0.01 | I12: -0.0069 | J12: 0.0073 | K12: -0.0053 | L12: -0.0146 | M12: 0.001 | N12: 0.09 | O12: 0.0008 | P12: 0.69 | Q12: 0.32 | R12: 0.977 | S12: 0.87 | T12: 20081231 | U12: 20190731 | V12: 128
A13: cur | B13: 0.0028 | C13: -0.0076 | D13: 0.006 | E13: 0.0147 | F13: 0.0064 | G13: -0.0259 | H13: -0.0012 | I13: -0.0102 | J13: -0.0026 | K13: 0.0137 | L13: -0.0078 | M13: -0.001 | N13: -0.06 | O13: 0.0003 | P13: 0.16 | Q13: 0.11 | R13: 0.978 | S13: 0.97 | T13: 20081231 | U13: 20190731 | V13: 128
... A64: z | B64: -0.0243 | C64: 0.006 | D64: -0.0129 | E64: -0.0041 | F64: 0.0283 | G64: -0.0729 | H64: -0.0098 | I64: -0.0678 | J64: -0.0316 | K64: -0.0034 | L64: -0.0119 | M64: -0.019 | N64: -0.75 | O64: -0.001 | P64: -0.35 | Q64: -0.3 | R64: 0.999 | S64: 0.97 | T64: 20081231 | U64: 20190731 | V64: 128

Sheet 质量因子_zz800
A1: sig.name | B1: X2009 | C1: X2010 | D1: X2011 | E1: X2012 | F1: X2013 | G1: X2014 | H1: X2015 | I1: X2016 | J1: X2017 | K1: X2018 | L1: X2019 | M1: rank.ic | N1: rank.ic.ir | O1: coef.estimate | P1: coef.ir | Q1: coef.t | R1: sig.coverage | S1: cor.with.pre.period | T1: min.date | U1: max.date | V1: period.count
A2: abacc | B2: 0.0216 | C2: 0.0042 | D2: 0.001 | E2: 0.004 | F2: 0.0227 | G2: 0.0298 | H2: -0.0071 | I2: 0.0231 | J2: -0.0081 | K2: 0.0244 | L2: 0.0023 | M2: 0.011 | N2: 0.76 | O2: 0.0011 | P2: 0.73 | Q2: 0.36 | R2: 0.872 | S2: 0.91 | T2: 20081231 | U2: 20190731 | V2: 128
A3: abaccall | B3: 0.0232 | C3: -0.0032 | D3: 0.0018 | E3: 0.0091 | F3: 0.0291 | G3: 0.0242 | H3: 0.0017 | I3: 0.011 | J3: -0.0101 | K3: 0.0177 | L3: 0.0117 | M3: 0.011 | N3: 0.76 | O3: 0.0012 | P3: 0.83 | Q3: 0.4 | R3: 0.974 | S3: 0.93 | T3: 20081231 | U3: 20190731 | V3: 128
A4: acc1 | B4: 0.0115 | C4: 0.0034 | D4: -0.003 | E4: -0.0005 | F4: 0.0151 | G4: 0.034 | H4: -0.015 | I4: 0.021 | J4: -0.0042 | K4: 0.0282 | L4: 0.0178 | M4: 0.01 | N4: 0.61 | O4: 0.0009 | P4: 0.56 | Q4: 0.31 | R4: 0.89 | S4: 0.94 | T4: 20081231 | U4: 20190731 | V4: 128
A5: acca | B5: 0.0195 | C5: -0.0043 | D5: -0.0023 | E5: -0.0045 | F5: 0.0059 | G5: 0.0315 | H5: -0.0085 | I5: 0.0216 | J5: 0.0034 | K5: 0.0261 | L5: 0.0237 | M5: 0.01 | N5: 0.65 | O5: 0.001 | P5: 0.64 | Q5: 0.34 | R5: 0.998 | S5: 0.93 | T5: 20081231 | U5: 20190731 | V5: 128
A6: bab | B6: 0.0321 | C6: 0.0297 | D6: 0.0267 | E6: 0.0247 | F6: 0.0426 | G6: 0.0442 | H6: 0.0451 | I6: 0.0296 | J6: -0.0071 | K6: 0.011 | L6: -0.018 | M6: 0.025 | N6: 1.26 | O6: 0.0012 | P6: 0.66 | Q6: 0.32 | R6: 0.848 | S6: 0.95 | T6: 20081231 | U6: 20190731 | V6: 128
A7: ccr | B7: 0.0248 | C7: 0.0109 | D7: 0.0166 | E7: 0.0188 | F7: 0.017 | G7: -0.0003 | H7: 0.0207 | I7: 0.0337 | J7: 0.0365 | K7: 0.0577 | L7: 0.0342 | M7: 0.024 | N7: 1.77 | O7: 0.0017 | P7: 1.08 | Q7: 0.52 | R7: 0.947 | S7: 0.95 | T7: 20081231 | U7: 20190731 | V7: 128
A8: ccrd | B8: 0.0179 | C8: -0.0065 | D8: 0.0116 | E8: -0.0009 | F8: 0.0329 | G8: 0.0049 | H8: 0.0111 | I8: 0.0048 | J8: 0.0105 | K8: 0.0003 | L8: 0.0052 | M8: 0.008 | N8: 0.79 | O8: 0.0008 | P8: 0.68 | Q8: 0.24 | R8: 0.932 | S8: 0.87 | T8: 20081231 | U8: 20190731 | V8: 128
A9: cd2d | B9: 0.0045 | C9: 0.0048 | D9: -0.002 | E9: -0.003 | F9: 0.0063 | G9: -0.0373 | H9: 0.0158 | I9: 0.008 | J9: 0.0255 | K9: 0.0193 | L9: 0.0276 | M9: 0.006 | N9: 0.37 | O9: 0.0007 | P9: 0.54 | Q9: 0.27 | R9: 0.948 | S9: 0.98 | T9: 20081231 | U9: 20190731 | V9: 128
A10: cfovol2a | B10: -0.0038 | C10: -0.0032 | D10: -0.0097 | E10: 0.0085 | F10: 0.0026 | G10: -0.0366 | H10: 0.0053 | I10: -0.0102 | J10: 0.0182 | K10: -0.0393 | L10: 0.0068 | M10: -0.006 | N10: -0.43 | O10: -0.0001 | P10: -0.08 | Q10: -0.05 | R10: 0.997 | S10: 0.97 | T10: 20081231 | U10: 20190731 | V10: 128
A11: cr | B11: 0.0051 | C11: -0.0064 | D11: 0.0221 | E11: 0.0217 | F11: -0.0156 | G11: -0.0214 | H11: 0.004 | I11: -0.007 | J11: 0.0043 | K11: 0.0273 | L11: 0.0145 | M11: 0.004 | N11: 0.23 | O11: 0.0005 | P11: 0.35 | Q11: 0.14 | R11: 0.949 | S11: 0.97 | T11: 20081231 | U11: 20190731 | V11: 128
A12: crd | B12: -0.0125 | C12: 0.0143 | D12: 0.0177 | E12: 0.0259 | F12: -0.0191 | G12: 0.0087 | H12: -0.0138 | I12: 0.0219 | J12: 0.0194 | K12: 0.0011 | L12: -0.0585 | M12: 0.002 | N12: 0.14 | O12: 0.001 | P12: 0.7 | Q12: 0.24 | R12: 0.947 | S12: 0.87 | T12: 20081231 | U12: 20190731 | V12: 128
A13: cur | B13: 0.0038 | C13: -0.0041 | D13: 0.0166 | E13: 0.0265 | F13: -0.0158 | G13: -0.0237 | H13: -0.0076 | I13: -0.0018 | J13: 0.0223 | K13: 0.0269 | L13: -0.0019 | M13: 0.004 | N13: 0.22 | O13: 0.0004 | P13: 0.26 | Q13: 0.13 | R13: 0.949 | S13: 0.97 | T13: 20081231 | U13: 20190731 | V13: 128
... A64: z | B64: -0.0224 | C64: -0.0005 | D64: -0.0002 | E64: 0.0069 | F64: 0.018 | G64: -0.0763 | H64: -0.0212 | I64: -0.04 | J64: 0.029 | K64: 0.0299 | L64: 0.0364 | M64: -0.005 | N64: -0.2 | O64: -0.0002 | P64: -0.08 | Q64: 0.13 | R64: 0.999 | S64: 0.97 | T64: 20081231 | U64: 20190731 | V64: 128

Sheet 因子初步筛选汇总
A1: 主题 | B1: 子主题 | C1: 信号 | D1: 原始IC | E1: 优化后IC | F1: 操作 | G1: 优化说明 | I1: 行标签 | J1: 计数项:信号 | K1: 平均值项:原始IC | L1: 平均值项:优化后IC
A2: 成长 | B2: 比值 | C2: con_peg_roll | D2: 0.029 | F2: 不变 | I2: 不变 | J2: 63 | K2: 0.034885246
A3: 成长 | B3: 比值 | C3: npegl | D3: 0.033 | E3: 0.047 | F3: 优化 | I3: 新增 | J3: 29 | K3: 0.033172414
A4: 成长 | B4: 比值 | C4: npegs | D4: 0.024 | E4: 0.037 | F4: 优化 | I4: 优化 | J4: 31 | K4: 0.034406452 | L4: 0.0399125
A5: 成长 | B5: 比值 | C5: qop2qlgae | D5: 0.038 | F5: 新增 | I5: (空白)
A6: 成长 | B6: 比值 | C6: qtor2qtoc | D6: 0.035 | F6: 新增 | I6: 总计 | J6: 123 | K6: 0.034352066 | L6: 0.0399125
A7: 成长 | B7: 超预期类 | C7: smarg | D7: 0.016 | F7: 不变
A8: 成长 | B8: 超预期类 | C8: sue | D8: 0.04 | F8: 不变 | I8: 行标签 | J8: 计数项:信号 | K8: 平均值项:原始IC | L8: 平均值项:优化后IC
A9: 成长 | B9: 超预期类 | C9: suoi | D9: 0.039 | F9: 不变 | I9: 不变 | J9: 63 | K9: 0.034885246
A10: 成长 | B10: 超预期类 | C10: sup_con_np_yg | D10: 0.035 | E10: 0.047 | F10: 优化 | G10: 增加预告数据 | I10: 成长 | J10: 11 | K10: 0.027909091
A11: 成长 | B11: 超预期类 | C11: supad | D11: 0.014 | F11: 不变 | I11: 价值 | J11: 16 | K11: 0.040625
A12: 成长 | B12: 超预期类 | C12: sus | D12: 0.028 | F12: 新增 | I12: 情绪 | J12: 12 | K12: 0.052
A13: 成长 | B13: 同比变化 | C13: nqdroe | D13: 0.04 | E13: 0.043 | F13: 优化 | G13: 增加快报和预告数据 | I13: 分析师 | J13: 7 | K13: 0.0244
A14: 成长 | B14: 同比变化 | C14: qdroa | D14: 0.036 | F14: 不变 | I14: 质量 | J14: 17 | K14: 0.025
A15: 成长 | B15: 同比变化 | C15: roeg_ttm | D15: 0.02 | F15: 新增 | I15: 新增 | J15: 29 | K15: 0.033172414
A16: 成长 | B16: 同比变化 | C16: epsg_ttm | D16: 0.018 | F16: 新增 | I16: 成长 | J16: 19 | K16: 0.030526316
A17: 成长 | B17: 同比变化占比 | C17: da2ev | D17: 0.024 | F17: 不变 | I17: 情绪 | J17: 8 | K17: 0.040875
A18: 成长 | B18: 同比变化占比 | C18: dafc2ia | D18: 0.022 | F18: 新增 | I18: 质量 | J18: 2 | K18: 0.0275
A19: 成长 | B19: 同比变化占比 | C19: dqop2qcpbe | D19: 0.036 | F19: 不变 | I19: 优化 | J19: 31 | K19: 0.034406452 | L19: 0.0399125
A20: 成长 | B20: 同比变化占比 | C20: ds2p | D20: 0.027 | F20: 不变 | I20: 成长 | J20: 7 | K20: 0.035285714 | L20: 0.042857143
A21: 成长 | B21: 同比变化占比 | C21: fes2 | D21: 0.014 | F21: 不变 | I21: 价值 | J21: 4 | K21: 0.03925 | L21: 0.060666667
A22: 成长 | B22: 同比变化占比 | C22: nde2p | D22: 0.044 | E22: 0.05 | F22: 优化 | G22: 增加快报和预告数据 | I22: 情绪 | J22: 6 | K22: 0.049166667 | L22: 0.05
A23: 成长 | B23: 同比变化占比 | C23: nds2ev | D23: 0.034 | E23: 0.035 | F23: 优化 | G23: 增加快报和预告数据 | I23: 分析师 | J23: 12 | K23: 0.027758333 | L23: 0.0255875
A24: 成长 | B24: 同比变化占比 | C24: nfes1 | D24: 0.037 | E24: 0.041 | F24: 优化 | G24: 增加快报和预告数据 | I24: 质量 | J24: 2 | K24: 0.01725 | L24: 0.0212
A25: 成长 | B25: 统计指标 | C25: rrqop_qcpacf | D25: 0.036 | F25: 新增 | I25: (空白)
A26: 成长 | B26: 统计指标 | C26: rrqop_qncfoa | D26: 0.036 | F26: 新增 | I26: (空白)
A27: 成长 | B27: 增长率对比 | C27: rqnp_rqcpbe | D27: 0.032 | F27: 新增 | I27: 总计 | J27: 123 | K27: 0.034352066 | L27: 0.0399125
A28: 成长 | B28: 增长率对比 | C28: rqop_rcpg | D28: 0.029 | F28: 新增
A29: 成长 | B29: 增长率对比 | C29: rqop_rqcpbe | D29: 0.032 | F29: 新增
A30: 成长 | B30: 增长率对比 | C30: rqop_rqlgae | D30: 0.031 | F30: 新增
A31: 成长 | B31: 增长率类 | C31: cfg_ttm | D31: 0.019 | F31: 新增
A32: 成长 | B32: 增长率类 | C32: da2a | D32: 0.039 | F32: 新增
A33: 成长 | B33: 增长率类 | C33: ne2e_q | D33: 0.049 | F33: 新增
A34: 成长 | B34: 增长率类 | C34: npg_q | D34: 0.026 | F34: 新增
A35: 成长 | B35: 增长率类 | C35: nqcsg | D35: 0.032 | F35: 不变
A36: 成长 | B36: 增长率类 | C36: opg_q | D36: 0.041 | F36: 新增
A37: 成长 | B37: re | C37: opg_ttm | D37: 0.023 | F37: 新增
A38: 成长 | B38: 增长率类 | C38: org_ttm | D38: 0.026 | F38: 新增
A39: 价值 | B39: value_bv | C39: b2p | D39: 0.046 | E39: 0.069 | F39: 优化 | G39: 根据最近20天的b2p相关性，增加相关性高部分的分数，降低相关性低的分数。换手率大幅提高
A40: 价值 | B40: value_bv | C40: con_pb_roll | D40: 0.051 | F40: 不变
A41: 价值 | B41: value_bv | C41: con_ps_roll | D41: 0.026 | F41: 不变
A42: 价值 | B42: value_bv | C42: nb2p | D42: 0.035 | F42: 不变
A43: 价值 | B43: value_bv | C43: nsale2ev | D43: 0.029 | F43: 不变
A44: 价值 | B44: value_bv | C44: s12ev | D44: 0.024 | E44: 0.053 | F44: 优化 | G44: 根据最近20天的b2p相关性，增加相关性高部分的分数，降低相关性低的分数。换手率大幅提高
A45: 价值 | B45: value_bv | C45: s23ev | D45: 0.026 | F45: 不变
A46: 价值 | B46: value_bv | C46: sale2ev | D46: 0.029 | E46: 0.06 | F46: 优化 | G46: 根据最近20天的b2p相关性，增加相关性高部分的分数，降低相关性低的分数。换手率大幅提高
A47: 价值 | B47: value_bv | C47: sale2p | D47: 0.027 | F47: 不变
A48: 价值 | B48: value_bv | C48: ta2ev | D48: 0.039 | F48: 不变
A49: 价值 | B49: value_bv | C49: b2paddcor20
A50: 价值 | B50: value_bv | C50: s12evaddcor20
A51: 价值 | B51: value_bv | C51: s23evaddcor20
A52: 价值 | B52: value_bv | C52: sale2evaddcor20
A53: 价值 | B53: value_bv | C53: ta2evaddcor20
A54: 价值 | B54: value_cf | C54: aeb2evaddcor20
A55: 价值 | B55: value_cf | C55: cfo2evaddcor20
A56: 价值 | B56: value_dvd | C56: d2paddcor20
A57: 价值 | B57: value_pe | C57: fy12paddcor20
A58: 价值 | B58: value_pe | C58: fy23paddcor20
A59: 价值 | B59: value_pe | C59: ne2paddcor20
A60: 价值 | B60: value_bv | C60: b2paddcor60
... A70: 价值 | B70: value_pe | C70: ne2paddcor60
A71: 价值 | B71: value_cf | C71: aeb2ev | D71: 0.029 | F71: 不变
A72: 价值 | B72: value_cf | C72: cfo2ev | D72: 0.037 | F72: 不变
A73: 价值 | B73: value_cf | C73: cfo2p | D73: 0.031 | F73: 不变
A74: 价值 | B74: value_dvd | C74: d2p | D74: 0.042 | F74: 不变
A75: 价值 | B75: value_pe | C75: con_pe_roll | D75: 0.058 | F75: 不变
A76: 价值 | B76: value_pe | C76: e2p | D76: 0.053 | F76: 不变
A77: 价值 | B77: value_pe | C77: fy12p | D77: 0.058 | F77: 不变
A78: 价值 | B78: value_pe | C78: fy23p | D78: 0.058 | F78: 不变
A79: 价值 | B79: value_pe | C79: ke2p | D79: 0.051 | F79: 不变
A80: 价值 | B80: value_pe | C80: ne2p | D80: 0.058 | F80: 优化 | G80: 使用预告和快报的数据表现更好
A81: 情绪 | B81: 波动率 | C81: ivo_ff12m | D81: 0.064 | F81: 新增 | G81: 换手率低，使用于构建月度以上
A82: 情绪 | B82: 波动率 | C82: ivo_ff1m | D82: 0.092 | F82: 不变
A83: 情绪 | B83: 波动率 | C83: ivr_ff12m | D83: 0.055 | F83: 新增 | G83: 换手率低，使用于构建月度以上
A84: 情绪 | B84: 波动率 | C84: ivr_ff1m | D84: 0.08 | F84: 不变
A85: 情绪 | B85: 波动率 | C85: volatility_12m | D85: 0.061 | E85: 0.061 | F85: 优化 | G85: 真实收益率的收益率更高，IR更高
A86: 情绪 | B86: 波动率 | C86: volatility_1m | D86: 0.07 | E86: 0.076 | F86: 优化 | G86: 真实收益率的收益率更高，IR更高
A87: 情绪 | B87: 波动率 | C87: volatility_actual12m | D87: 0.061 | E87: 0.076 | F87: 优化 | G87: 实际波动率
A88: 情绪 | B88: 波动率 | C88: volatility_actual1m | D88: 0.07 | E88: 0.076 | F88: 优化 | G88: 实际波动率
A89: 情绪 | B89: 动量 | C89: cthl12m | D89: 0.02 | F89: 新增 | G89: 隔日动量，根据高开/低开，计算当日收益
A90: 情绪 | B90: 动量 | C90: cthl6m | D90: 0.022 | F90: 新增 | G90: 隔日动量，根据高开/低开，计算当日收益
A91: 情绪 | B91: 动量 | C91: cto12m | D91: 0.022 | F91: 新增 | G91: 隔日动量
A92: 情绪 | B92: 动量 | C92: cto6m | D92: 0.023 | F92: 新增 | G92: 隔日动量
A93: 情绪 | B93: 动量 | C93: demom10 | D93: -0.003 | E93: 0.02 | F93: 优化 | G93: drmom9m，采用收益率和正收益率胜率双排序
A94: 情绪 | B94: 动量 | C94: demom7 | D94: -0.002 | E94: 0.021 | F94: 优化 | G94: drmom7m，采用收益率和正收益率胜率双排序
A95: 情绪 | B95: 动量 | C95: maxret33 | D95: 0.064 | F95: 新增 | G95: 最近3个月收益率最高3天的均值
A96: 情绪 | B96: 动量 | C96: maxret66 | D96: 0.057 | F96: 新增 | G96: 最近6个月收益率最高6天的均值
A97: 情绪 | B97: 动量 | C97: momentum | D97: 0.003 | F97: 不变 | G97: 风险模型动量
A98: 情绪 | B98: 动量 | C98: momentum_t12 | D98: 0.006 | F98: 不变
A99: 情绪 | B99: 反转 | C99: pairs | D99: 0.041 | F99: 不变
A100: 情绪 | B100: 反转 | C100: revs | D100: 0.075 | E100: 0.072 | F100: 优化 | G100: 使用每笔成交金额金额分割，构建因子。IC稍有下降，但IR大幅提高。从2.51变为4.5。
A101: 情绪 | B101: 反转 | C101: spb | D101: 0.072 | F101: 不变
A102: 情绪 | B102: 价值反转 | C102: rcon_peg_roll | D102: 0.042 | F102: 不变 | G102: 结合财务数据和价格变化
A103: 情绪 | B103: 价值反转 | C103: rfy12p | D103: 0.059 | F103: 不变 | G103: 结合财务数据和价格变化
A104: 情绪 | B104: 价值反转 | C104: rpegs | D104: 0.041 | F104: 不变 | G104: 结合财务数据和价格变化
A105: 情绪 | B105: 流动性 | C105: davol | D105: 0.047 | F105: 不变
A106: 情绪 | B106: 流动性 | C106: illiq | D106: 0.061 | F106: 不变 | G106: 非流动性因子
A107: 情绪 | B107: 流动性 | C107: liquidty | D107: 0.08 | F107: 不变 | G107: 0.35 · STOM + 0.35 · STOQ + 0.30 · STOA
A108: 情绪 | B108: 流动性 | C108: vol | D108: 0.094 | F108: 优化 | G108: 自由流通股本换手率
A109: 分析师 | B109: cov | C109: cvg_og3 | D109: 0.0461 | E109: 0.0467 | F109: 优化 | G109: 同一机构不同日期算多次
...
